Workbook

Sheet Consent Features and Weights
A1: Cateogory | B1: Weights (fin not avail) | C1: Financial: | D1: Table | E1: mapping key | F1: direct json keys | H1: Weights (fin avail) | I1: Accuracy in feature value when automated (cannot have high weightage when accurcy of computation is low) | J1: Max score | K1: Sources | O1: Tara Grains | P1: SPCL | Q1: Spectrum Builtech | R1: 0.7 | S1: Core | U1: Count of non core available | V1: Weightage for core | W1: Weightage for non core
A2: Financials | B2: 100 | C2: All fin features | K2: Tally | R2: 0.3 | S2: Non core | U2: 0 to 2 | V2: 90 | W2: 10
A3: Financials | B3: 70 | C3: All fin features - unaudited / provisional | K3: Tally | U3: 3 to 4 | V3: 80 | W3: 20
U4: >=5 | V4: 70 | W4: 30
A5: For Multiple accounts, 1) Feature values and scores will be calculated individually. 2) Final score to the model will be simple average of Step 1 scores wherein denominator would be count of accounts where values could be calculated
A7: Liquidity | B7: 20 | C7: wc_utilisation_lxm_BSA_Tally | D7: EOD Balances | E7: percent_util_during_period_on_limit | F7: 1. Applicable only if count of "monthName" where "xnscount "> 0 is greater than 6 2. Numerator : monthly_details > average of "balavg" of last 12 months where "xnscount "> 0 3. sanctioned_limit from bureau json 4. (Step 1 / Step 2) * (-100) old: 1. analysis_summary_info > Account Type = contains "cash credit", "cc", "od", "over draft" 2. sum of (analysis_month_wise_average_eod_balance) for all months divide by no of months 3. compute: Step 2 * 100 / (sanctioned_limit * -1) | H7: 30 | I7: High | K7: BS, Tally | P7: Y | R7: Scores | S7: Scores
B8: 20 | C8: percent_months_amb_lower_than_apb | E8: count_months_amb_less_than_avg_os_balance_period = in analysis sheet period_months - basic info sheet | F8: (count_months_amb_less_than_avg_os_balance_period / period_months) * 100 | K8: BS
A9: Liquidity | B9: 10 | C9: wc_utilisation_l6m_BSA_Tally | D9: EOD Balances | E9: percent_util_during_l6m_on_limit | F9: 1. Numerator : monthly_details > average of "balavg" of last 6 months where "xnscount "> 0 2. sanctioned_limit from bureau json 3. (Step 1 / Step 2) * (-100) old: 1. analysis_summary_info > Account Type = contains "cash credit", "cc", "od", "over draft" 2. sum of (analysis_month_wise_average_eod_balance) for all months divide by no of months 3. compute: Step 2 * 100 / (sanctioned_limit * -1) | H9: 0 | I9: High | K9: BS | P9: Y | R9: 30 | S9: 30
B10: 10 | C10: % change in avg outstanding balance | F10: per_change_outstanding_balance | K10: BS
A11: Credit protection | B11: 20 | C11: effective_interest_rate_BSA_Tally | D11: Statement | E11: effective_interest_rate_period | F11: Only applicable to Od / CC / WC accounts: Numerator : 1. xns > filter "Category" contains "Interest Charges" - > sum of "amount" fields -> If negative, then take absolute value 2. Step 1 divide by "no of months" computed in step 2 to get avg interest charges Denominator : 3. "balance" at the end of each day 4. filter only "balance" < 0 5. Simple avg of Step 4 6. Absolute of Step 5 7.( Step 2 / Step 6) * 12*100 1. sum of "analysis_month_wise_average_eod_balance" for all months divide by 'no of months'. If negative, then take absolute value 2. xns > filter "Category" contains "Interest Charges" - > sum of "amount" fields -> If negative, then take absolute value 3. Step 2 divide by "no of months" computed in step 2 to get avg interest charges 4.( Step 1 / Step 3) * 12*100 If Step 2 is 0, then this feature is NA | I11: High | K11: BS, Tally | P11: Y | R11: 15 | S11: 15 | W11: color | X11: score
A12: Liquidity | B12: 20 | C12: churn_rate_BSA_tally | D12: BSA key summary - total (period | E12: churn_rate | F12: Numerator = analysis_month_wise_total_amount_of_debit_transactions for month 1 + analysis_month_wise_total_amount_of_debit_transactions for month 2 + analysis_month_wise_total_amount_of_debit_transactions till month n Denom = analysis_month_wise_total_amount_of_credit_transactions for month 1 + analysis_month_wise_total_amount_of_credit_transactionsfor month 2 + analysis_month_wise_total_amount_of_credit_transactions till month n num/denom * 100 | I12: High | K12: BS, Tally | P12: Y | R12: 0 | S12: 0
A13: Liquidity | B13: 10 | C13: Inward cheque returns_BSA_tally | D13: Cheque returns | E13: count_inward_return | F13: analysis_month_wise_total_number_of_inward_cheque_bounces for every month and then do sum for all months | I13: High | K13: BS, Tally | P13: Y | R13: -15 | S13: -15
A14: Liquidity | B14: 10 | C14: overutilisation_frequency_BSA_Tally | D14: EOD Balances | E14: days_overutilisations_in_a_period | F14: 1. "balance"*(-1) 2. count of Step 1 > sanction limit from bureau json old: 1. analysis_summary_info > Account Type = contains "cash credit", "cc", "od", "over draft" 2. in xns > filter for (outstanding balance * -1) > sanctioned limit 3. Take count of records | I14: High | K14: BS, Tally | P14: Y | R14: -30 | S14: -30
B15: 10 | C15: negative_balance_instances | F15: count_instances_negative_balance
A16: Liquidity | B16: 10 | C16: pre_post_loan_utilisation_BSA_tally | D16: EOD Balances | E16: refer Thresholds sheet | F16: ignore | I16: Low | K16: BS | P16: Y
B17: =sum(B7:B16) -> 140
A18: Liquidity | B18: 10 | C18: net_cashflow_movement _tally | I18: High | K18: Tally, BS | P18: Y
A19: Liquidity | B19: 10 | C19: customer_ageing_tally | I19: High | K19: Tally | P19: N
A20: Liquidity | B20: 10 | C20: supplier_ageing_tally | I20: High | K20: Tally | P20: N
A21: Liquidity | B21: 10 | C21: inventory_ageing_tally | I21: High | K21: Tally | P21: N
A22: Profitability | B22: 10 | C22: gross_profit_on_sales_GST_Tally | I22: High | K22: GST, Tally | P22: N
A23: Performance | B23: 10 | C23: growth in revenue tally | I23: High | K23: Tally
A24: Performance | B24: 10 | C24: growth in net profit tally | I24: High | K24: Tally
A25: Liquidity | B25: 0 | C25: avg_cash_balance_change_tally | I25: High | K25: Tally
A26: Performance | B26: 15 | C26: gross_sales_trend_gst_tally | F26: 1) Calculate latest 24 months using max month available in sales_trend or purchases_trend. Use this period in all gstn feature calculation. 2) Under "sales_trend" 3) sum of amount of latest 12 months determined in Step 1 4) sum of amount of previous 12 months determined in Step 1 5) ((Step 2/ Step 3) -1 )* 100 if Step 3 is not available (i.e. 24 months data not available, then this feature is NA | I26: High | K26: GST, Tally | P26: N
A27: Performance | B27: 15 | C27: gross_purchases_trend_gst_tally | F27: 1) Calculate latest 24 months using max month available in sales_trend or purchases_trend. Use this period in all gstn feature calculation. 2) Under "purchases_trend" 3) sum of amount of latest 12 months determined in Step 1 4) sum of amount of previous 12 months determined in Step 1 5) ((Step 2/ Step 3) -1 )* 100 if Step 3 is not available (i.e. 24 months data not available, then this feature is NA | I27: High | K27: GST, Tally | P27: N
B28: =SUM(B18:B27) -> 100
C31: Non Financial:
A32: Bureau | B32: 15 | C32: commercial_bureau_score | E32: commercial_bureau_score
A33: Bureau | B33: 5 | C33: retail_bureau_score | E33: retail_mfi_bureau_score
A34: Bureau | B34: 10 | C34: unsecured_loans_enquiries_l30d | E34: enquiry_unsec_loans_l30d / enquiry_all_l30d * 100
A35: Bureau | B35: 10 | C35: current_account_classification_rank | E35: 1.DelinquencySummary > AsBorrower > List all values under "CurrentAccountClassification" 2.Rank as per sheet "account_or_asset_classification" 3. Take max value of rank
A36: Bureau | B36: 10 | C36: historic_account_classification_rank | E36: 1.DelinquencySummary > AsBorrower > List all values under "MostSevere_DPD_AssetClass_Lst_48_Mths" Note: value seperated with "/" to be again made seperate 2.Rank as per sheet "account_or_asset_classification" 3. Take max value of rank
A37: Corporate governance | B37: 10 | C37: Significant_cash_transactions_amount_BSA_tally | D37: BSA key summary - total (period) | E37: cash_transction_as_percent_total_transactions | F37: num = for all months (analysis_month_wise_total_amount_of_cash_deposits + analysis_month_wise_total_amount_of_cash_withdrawals) denom = for all months (analysis_month_wise_total_amount_of_credit_transactions+ analysis_month_wise_total_amount_of_debit_transactions) num/denom * 100 | I37: Medium | K37: BS , Tally | P37: Y
A38: Corporate governance | B38: 10 | C38: Significant_cash_transactions_count_BSA_tally | D38: BSA key summary - total (period) | E38: count_cash_transactions | F38: [analysis_month_wise_total_number_of_cash_deposits + analysis_month_wise_total_number_of_cash_withdrawals] for all months | I38: Medium | K38: BS , Tally | P38: Y
A39: Business risk | B39: 10 | C39: customer_concentration_GST_Tally | D39: Customer Concentration | F39: Calculate latest 24 months using max month available in sales_trend or purchases_trend. Use this period in all gstn feature calculation. Under "sales_concentration" 1) sum of amount per gstn for latest 12 months 2) Under "sales_trend", sum of amount of latest 12 months 3) step 1 divided by Step 2 per gstn * 100 4) arrange gstn in descending order 5) sum of top 5 | I39: High | K39: GST, Tally | P39: N
A40: Business risk | B40: 10 | C40: supplier_concentration_GST_Tally | D40: Supplier Concentration | F40: Calculate latest 24 months using max month available in sales_trend or purchases_trend. Use this period in all gstn feature calculation. Under "purchase_concentration" 1) sum of amount per gstn for latest 12 months 2) Under "purchase_trend", sum of amount of latest 12 months 3) step 1 divided by Step 2 per gstn * 100 4) arrange gstn in descending order 5) sum of top 5 | I40: High | K40: GST, Tally | P40: N
A41: Liquidity | B41: 0 | C41: salary_payment_delay_Tally_BSA | I41: Low | K41: Tally , BS | P41: Y
A42: Corporate governance | B42: 10 | C42: routing_of_funds_BSA_tally | F42: under "partiesInCreditsAndDebits" < count of "partyName" | I42: Low | K42: BS , Tally | P42: Y
B43: =SUM(B32:B42) -> 100
A44: Corporate governance | B44: 15 | C44: Related_party_transactions_unrelated_LOB_ITR_Tally_BS_GST | I44: Low | K44: Tally + ITR, BS + ITR, GST+ITR | P44: N
A45: Business risk | B45: 5 | C45: product_concentration_Tally_gst | D45: Product Concentration | F45: Calculate latest 12 months using max month available in sales_trend or purchases_trend. Use this period in all gstn feature calculation. Under "hsn_summary_code_wise" 1) "hsn code" wise > do sum of "total_value" 2) Under "sales_trend", sum of amount of last 12 months 3) step 2 divided by Step 3 per hsn code wise * 100 4) arrange hsn code in descending order 5) sum of top 5 | I45: High | K45: Tally, GST | P45: N
A46: Business risk | B46: 20 | C46: geographic_concentration_GST | I46: High | K46: GST | P46: N
A47: Compliance | B47: 30 | C47: late_payment_fees_GST_Tally | F47: 1) sum of "ltfee_details" of last 1 year 2) Step 1 divided by total "pdcash" of last 1 year * 100 | I47: Medium | K47: GST , Tally | P47: N
A48: Business risk | B48: 15 | C48: applicable when (customer_concentration_GST_Tally) is not available: concentration_risk_funds received_from_top_5_sources_BS | D48: Remitter Concentration | F48: 1.Within "accounts_xns" > Group by sum of unique list of "category" having "Transfer from" 2.Arrange in descending order 3. Take sum of first five records in unique list 4. In "accounts_xns > filter "category" by contains "transfer from" 5. Do sum of all Amount field on step 4 filter 6. Compute: (Step 3 * 100) / Step 5 | I48: Medium | K48: BS | P48: Y
A49: Business risk | B49: 15 | C49: applicable when (customer_concentration_GST_Tally) is not available: concentration_risk_funds remitted_to_top_5_sources_BS | D49: Beneficiary Concentration | F49: 1.Within "accounts_xns" > Group by sum of unique list of "category" having "Transfer to" 2. Convert the sum in absolute values 3.Arrange in descending order 4. Take sum of first five records in unique list 5. In "accounts_xns > filter "category" by contains "transfer to" 6. Do sum of all Amount field on step 4 filter 7. Compute: (Step 3 * 100) / Step 5 | I49: Medium | K49: BS | P49: Y
B50: =SUM(B44:B49) -> 100
C53: New features
C54: Commodity price volatility
C55: Customer concentation with TSR rating and receivable days
C56: Supplier concentation with TSR rating and payable days
A57: Liquidity | B57: 10 | C57: DP less than sanctioned limit daily / monthly basis with 40% as margin (customise) | K57: Tally and BS | P57: N
A58: Corporate governance | B58: 10 | C58: Related Party Outstanding / Transactions | K58: ITR (3CD) and Tally | P58: N
A59: Corporate governance | B59: 10 | C59: Bank Reconciliation | K59: Tally and BS | P59: N
A60: Liquidity | B60: 10 | C60: No. of times Sanctioned limit is more than MPBF (75% of Working Capital Gap) Ratio of sanctioned limit to 75% of WC capital gap | K60: Tally and BS | P60: N
A61: Corporate governance | B61: 10 | C61: Utilisation despite huge cash balance | K61: Tally and BS | P61: N
A62: Liquidity | B62: 10 | C62: Working capital debt utilisation (basis drawing power) | P62: N
A63: Compliance | B63: 10 | C63: Delay in ITR filing
A64: Corporate governance | B64: 5 | C64: Inconsistencies between ITR filing and FS
C66: Override on model Score | G66: Penalty
C67: Funds Insufficient Cheque return | D67: xns | F67: count 1 when: account type is not cc/od under account_xns "category" = "Bounced I/W Cheque" and "amount" > "balance" take sum of counts of all such instances
C68: 1 time | G68: -10% on fin score
C69: 2 times | G69: -20% on fin score
C70: 3 to 5 | G70: -40% on fin model+ fin consent score with Max TSR score 20 | H70: Risk tree map liquidity section to take entire fin weitage of 80%, rest 20% would be for other fin params Colour for liquidity override to "0.01"
C71: > 5 times | G71: -50% on fin model+ fin consent score with Max TSR score 20 | H71: Risk tree map liquidity section to take entire fin weitage of 80%, rest 20% would be for other fin params Colour for liquidity override to "0.01"
C72: DPD/SMA | J72: BB
C73: 0 to 7 days | G73: -70% on fin score with max fin score at 15 and TSR score of 10 | H73: Risk tree map liquidity section to take entire fin weitage of 50%, rest 10% would be for other fin params | I73: 55 | J73: =I73*0.3 -> 16.5 | K73: 40 | L73: =K73*0.3 -> 12
C74: > 7 days | G74: D | H74: Risk tree map liquidity section to take total area of 50% with colour as 0.01
C76: Override on Fin Score | G76: Push consent fin score to
C77: > 100 No of times account remained over utilised in 365 days | D77: EOD Balances | E77: days_overutilisations_in_a_period | F77: 1. analysis_summary_info > Account Type = contains "cash credit", "cc", "od", "over draft" 2. sum of (analysis_month_wise_average_eod_balance) for all months divide by no of months 3. compute: Step 2 * 100 / (sanctioned_limit * -1) 4. filter records where step 3 is >100 5. take count of all such records 6. If count > 100 | G77: Very Bad fin score + rating max TSR score of 15 and fin score of 10 | H77: Risk tree map liquidity section to take entire fin weitage of 50%, rest 10% would be for other fin params
C78: WC capital utilisation is over 90% + effective interest rate is over 15% | D78: EOD Balances | E78: percent_util_during_period_on_limit > 90% and effective_interest_rate_period > 15% | F78: percent_util_during_period_on_limit > 90% and effective_interest_rate_period > 15% | G78: Very Bad fin score | H78: Nothing special

Sheet Copy of Thresholds and Scoring 
A1: Financial Consent Feature | B1: Thresholds | C1: Scores (without fin) | G1: Non Financial Consent Feature | H1: Thresholds | I1: Scores
A2: percent_months_amb_lower_than_apb | B2: more than 80% | C2: -30 | G2: CIBIL Alerts | H2: Written off credit facility Downgrade in CMR beyond 2 notches Breach in Utilisation by 10% (Similarly 5%, 15%, 20%) Dishonored cheque | I2: -30
B3: 60 to 80% | C3: -15 | G3: https://docs.google.com/spreadsheets/d/10ZsYPAvyLTeRQ48DaBE7oEcaa6RfoOp2/edit#gid=1683855733 | H3: Downgrade in CMR within 2 notches Deterioration in CMR Restructure credit facility | I3: -15
B4: 40 to 60% | C4: 0 | H4: Others | I4: 0
B5: 20 to 40% | C5: 15 | H5: Upgrade in CMR within 2 notches Improvement in CMR | I5: 15
B6: less than 20% | C6: 30 | H6: Upgrade in CMR beyond 2 notches | I6: 30
A8: % change in avg outstanding balance | B8: less than -40% | C8: -30 | G8: commercial_bureau_score | H8: 1 to 3 | I8: 0
B9: -40% to 0% | C9: -15 | H9: 4 and 5 | I9: -15
B10: 0% to 20% | C10: 0 | H10: 6 and 7 | I10: -30
B11: 20% to 60% | C11: 15 | H11: above 7 | I11: override
B12: over 60% | C12: 30
D13: Thresholds | E13: Scores (with fin) | G13: unsecured_loans_enquiries_l30d | H13: MostSevere_DPD_AssetClass_Lst_48_Mths = standard CurrentAccountClassification = standard | I13: 15
A14: effecttive interest rate_BSA | B14: >18% | C14: -30 | D14: >12% and (> ACB + 2%) | E14: -30 | F14: >18% | G14: Current account classification | H14: std | I14: 0
A15: improve thresholding from more data, CHG-1 | B15: 12-18% | C15: -15 | D15: over 80% + STB > 80% of total debt + int coverage less than 2 times or over 80% + STB > 80% of total debt + receivable days > 90 days | E15: -15 | F15: 12-18% | I15: -15
B16: 10-12% | C16: 0 | D16: 60 to 80% | E16: 0 | F16: 7-12% | I16: -30
B17: 5-10% | C17: 15 | D17: 40 to 60% | E17: 15 | F17: 5-7%
B18: 0-5% | C18: 30 | D18: less than 40% | E18: 30 | F18: 0-5%
A20: Churn rate_BSA | B20: X <90% | C20: 30
A21: improve with the use of churn trend | B21: 90 to 100 % | C21: 15
B22: 100 to 120% | C22: 0
B23: 120-150 % | C23: -15 | G23: Significant amount of cash transactions_BSA
B24: Greater than 150% | C24: -30
H25: < 2% | I25: 0
A26: Inward cheque returns_BSA_tally | H26: 2-5% | I26: -15
A27: (if CC account then cheque shouldnt bounce due to insufficient funds given it is within drawing power) | H27: > 5% | I27: -30
B28: 0 to 7 | C28: 0
B29: 8 to 14 | C29: -15 | G29: Significant number of cash transactions_BSA
B30: >=15 | C30: -30
H31: < 10 | I31: 0
A32: negative balance instances | B32: None | C32: 0 | H32: 10 to 20 | I32: -15
A33: improve basis continuous overutilisation and recency | B33: 0 to 5 | C33: 0 | H33: > 20 | I33: -30
B34: 6 to 15 | C34: -15
B35: over 15 | C35: -30 | G35: Customer concentration | H35: <10 | I35: 30
H36: 10 to 20 | I36: 15
H37: 20 to 50 | I37: 0
A38: overutilisation_frequency_BSA_Tally | B38: Never overutilised | C38: 0 | H38: 50-70 | I38: -15
A39: improve basis continuous overutilisation and recency | B39: 1 to 20 | C39: 0 | H39: >70 | I39: -30
B40: 0 | C40: 0
B41: 20 to 60 | C41: -15 | G41: Supplier concentration | H41: <10 | I41: 30
B42: > 60 | C42: -30 | H42: 10 to 20 | I42: 15
H43: 20 to 50 | I43: 0
H44: 50-70 | I44: -15
A45: pre_post_loan_utilisation_BSA_tally | B45: loan repayment > 0, any month post loan utilisation >=100% and pre loan utilisation < 100% or any month total credit transaction <= loan repaid | C45: -30 | D45: sum_loan_repayment_period > 0, percent_util_month_end_on_limit >=100% and pre_loan_repayment_utilisation_month_end < 100% or monthly_total_amount_of_credit_transactions <= sum_loan_repayment_month | H45: >70 | I45: -30
B46: loan repayment > 0, avg pre loan utilisation >= 80% and avg loan utilisation >= 5% | C46: -15 | D46: sum_loan_repayment_period > 0, avg_pre_loan_repayment_utilisation_period >= 80% and loan_utilisation_period >= 5%
B47: other scenarios | C47: 0 | G47: Salary payment trend | H47: 0 months | I47: 30
G48: From Min payment date of salary | H48: 1 month | I48: 15
G49: Salary payment not being classified correctly in perfious | H49: 2 months | I49: 0
H50: 3 months | I50: -15
A51: Net cashflow movement _Tally | B51: Less than -30% | C51: -30 | H51: > 3 months | I51: -30
B52: Less than 10% | C52: -15
B53: -10 to 20% | C53: 0
B54: 21 to 50% | C54: 15 | G54: routing_of_funds_BSA_tally
B55: more than 50% | C55: 30 | D55: avg rec = 45 | E55: credit period = 45 | G55: count of common records
H56: < 2 | I56: 0
A57: Customer Ageing | D57: 0-30 | E57: 30-60 | F57: 60-90 | H57: 2 to 5 | I57: -15
A58: receivables % less than credit period | B58: more than 20 | C58: 30 | D58: 60 | E58: 30 | F58: 10 | H58: > 5 | I58: -30
A59: receivables % less than credit period | B59: 10 to 20 | C59: 15
A60: receivables % less than credit period | B60: 0-10 | C60: 0 | D60: =F58/F60 -> 70 | F60: =F58/70 -> 0.14285714 | G60: Related party transactions_unrelated LOB | H60: 0 to 2% | I60: 30
A61: receivables % more than Avg receivable days of last 3 /2 /1 years | B61: 0-10 | C61: 0 | H61: 2-5% | I61: 15
A62: receivables % more than Avg receivable days of last 3 /2 /1 years | B62: 10 to 20 | C62: -15 | H62: 5-10% | I62: 0
A63: receivables % more than Avg receivable days of last 3 /2 /1 years | B63: more than 20 | C63: -30 | H63: 20-10% | I63: -15
H64: > 20% | I64: -30
A66: Supplier Ageing | G66: Product concentration | H66: <10 | I66: 30
A67: payables % less than credit period | B67: more than 20 | C67: 30 | H67: 10 to 15 | I67: 15
A68: payables % less than credit period | B68: 10 to 20 | C68: 15 | H68: 15 to 20 | I68: 0
A69: payables % less than credit period | B69: 0-10 | C69: 0 | H69: 20-50 | I69: -15
A70: payables % more than Avg payable days of last 3 /2 /1 years | B70: 0-10 | C70: 0 | H70: >50 | I70: -30
A71: payables % more than Avg payable days of last 3 /2 /1 years | B71: 10 to 20 | C71: -15
A72: payables % more than Avg payable days of last 3 /2 /1 years | B72: more than 20 | C72: -30 | G72: Geographic concentration | H72: <10 | I72: 30
H73: 10 to 15 | I73: 15
A74: Inventory Ageing | H74: 15 to 20 | I74: 0
A75: inventory % less than Avg inventory days of last 3 /2 /1 years | B75: more than 20 | C75: 30 | H75: 20-50 | I75: -15
A76: inventory % less than Avg inventory days of last 3 /2 /1 years | B76: 10 to 20 | C76: 15 | H76: >50 | I76: -30
A77: inventory % less than Avg inventory days of last 3 /2 /1 years | B77: 0-10 | C77: 0
A78: payables % more than Avg inventory days of last 3 /2 /1 years | B78: 0-10 | C78: 0 | G78: GST late payments
A79: payables % more than Avg inventory days of last 3 /2 /1 years | B79: 10 to 20 | C79: -15 | H79: sum of late fees is 0 in l12m | I79: 15
A80: payables % more than Avg inventory days of last 3 /2 /1 years | B80: more than 20 | C80: -30 | H80: < 5% and lt fees in l6m < lt fees (l12m - l6m) | I80: 0
H81: lt fees in l6m > lt fees (l12m - l6m) or 5 to 15% | I81: -15
A82: growth_annual_revenue_tally | B82: < - 10% | C82: -30 | G82: ` | H82: (lt fees in l6m > lt fees (l12m - l6m) and 5 to 15%) OR > 15% | I82: -30
B83: - 10 to 0 | C83: -15
B84: 0 to 20 | C84: 0 | G84: Concentration risk - funds received from top 5 sources | H84: <10 | I84: 30
B85: > 20 to 50 | C85: 15 | H85: 10 to 20 | I85: 15
B86: > 50 | C86: 30 | H86: 20 to 40 | I86: 0
H87: 40-60 | I87: -15
A88: growth_annual_netprofit_tally | B88: < - 10% | C88: -30 | H88: >60 | I88: -30
B89: - 10 to 0 | C89: -15
B90: 0 to 20 | C90: 0 | G90: Concentration risk - funds remitted to top 5 | H90: <10 | I90: 30
B91: > 20 to 50 | C91: 15 | H91: 10 to 20 | I91: 15
B92: > 50 | C92: 30 | H92: 20 to 40 | I92: 0
H93: 40-60 | I93: -15
A94: gross sales trend_gst | B94: < - 10% | C94: -30 | H94: >60 | I94: -30
B95: - 10 to 0 | C95: -15
B96: 0 to 20 | C96: 0
B97: > 20 to 50 | C97: 15
B98: > 50 | C98: 30
A100: gross purchases trend_gst | B100: < - 10% | C100: -30
B101: - 10 to 0 | C101: -15
B102: 0 to 20 | C102: 0
B103: > 20 to 50 | C103: 15
B104: > 50 | C104: 30
...

Sheet Thresholds and Scoring
A1: Financial Consent Feature | B1: Thresholds | C1: Scores (without fin) | D1: Thresholds | E1: Scores (with fin) | G1: Non Financial Consent Feature | H1: Thresholds | I1: Scores
A2: WC utilisation_bank statement _BSA_ltm | B2: more than 95% | C2: -30 | D2: over 80% + int coverage less than 1.5 times or over 80% + WC days over 90 | E2: -30 | G2: CIBIL Alerts | H2: Written off credit facility Downgrade in CMR beyond 2 notches Breach in Utilisation by 10% (Similarly 5%, 15%, 20%) Dishonored cheque | I2: -30
B3: 80-95% | C3: -15 | D3: over 80% + STB > 80% of total debt + int coverage less than 2 times or over 80% + STB > 80% of total debt + receivable days > 90 days | E3: -15 | G3: https://docs.google.com/spreadsheets/d/10ZsYPAvyLTeRQ48DaBE7oEcaa6RfoOp2/edit#gid=1683855733 | H3: Downgrade in CMR within 2 notches Deterioration in CMR Restructure credit facility | I3: -15
B4: 60 to 80% | C4: 0 | D4: 80 to 85% + int coverage > 2 times | E4: 0 | H4: Others | I4: 0
B5: 40 to 60% | C5: 15 | D5: 60 to 80% + int coverage > 2 times | E5: 15 | H5: Upgrade in CMR within 2 notches Improvement in CMR | I5: 15
B6: less than 40% | C6: 30 | D6: less than 40% | E6: 30 | H6: Upgrade in CMR beyond 2 notches | I6: 30
A8: WC utilisation_bank statement _BSA_l6m | B8: more than 95% | C8: -30 | G8: Significant amount of cash transactions_BSA
B9: 80-95% | C9: -15
B10: 60 to 80% | C10: 0 | H10: < 2% | I10: 0
B11: 40 to 60% | C11: 15 | H11: 2-5% | I11: -15
B12: less than 40% | C12: 30 | H12: > 5% | I12: -30
D13: Thresholds | E13: Scores (with fin)
A14: effecttive interest rate_BSA | B14: >18% | C14: -30 | D14: >12% and (> ACB + 2%) | E14: -30 | G14: Significant number of cash transactions_BSA
A15: improve thresholding from more data, CHG-1 | B15: 12-18% | C15: -15 | D15: over 80% + STB > 80% of total debt + int coverage less than 2 times or over 80% + STB > 80% of total debt + receivable days > 90 days | E15: -15
B16: 10-12% | C16: 0 | D16: 60 to 80% | E16: 0 | H16: < 10 | I16: 0
B17: 5-10% | C17: 15 | D17: 40 to 60% | E17: 15 | H17: 10 to 20 | I17: -15
B18: 0-5% | C18: 30 | D18: less than 40% | E18: 30 | H18: > 20 | I18: -30
A20: Churn rate_BSA | B20: X <90% | C20: 30 | G20: Customer concentration | H20: <10 | I20: 30
A21: improve with the use of churn trend | B21: 90 to 100 % | C21: 15 | H21: 10 to 15 | I21: 15
B22: 100 to 120% | C22: 0 | H22: 15 to 20 | I22: 0
B23: 120-150 % | C23: -15 | H23: 20-50 | I23: -15
B24: Greater than 150% | C24: -30 | H24: >50 | I24: -30
A26: Inward cheque returns_BSA_tally | G26: Supplier concentration | H26: <10 | I26: 30
A27: (if CC account then cheque shouldnt bounce due to insufficient funds given it is within drawing power) | H27: 10 to 15 | I27: 15
B28: 0 to 7 | C28: 0 | H28: 15 to 20 | I28: 0
B29: 8 to 14 | C29: -15 | H29: 20-50 | I29: -15
B30: >=15 | C30: -30 | H30: >50 | I30: -30
A32: No of times account remained over utilised in 365 days(negative factor only) | B32: Never overutilised | C32: 0 | G32: Salary payment trend | H32: 0 months | I32: 30
A33: improve basis continuous overutilisation and recency | B33: 1 to 20 | C33: 0 | G33: From Min payment date of salary | H33: 1 month | I33: 15
B34: 0 | C34: 0 | G34: Salary payment not being classified correctly in perfious | H34: 2 months | I34: 0
B35: 20 to 60 | C35: -15 | H35: 3 months | I35: -15
B36: > 60 | C36: -30 | H36: > 3 months | I36: -30
A39: pre_post_loan_utilisation_BSA_tally | B39: loan repayment > 0, any month post loan utilisation >=100% and pre loan utilisation < 100% or any month total credit transaction <= loan repaid | C39: -30 | D39: sum_loan_repayment_period > 0, percent_util_month_end_on_limit >=100% and pre_loan_repayment_utilisation_month_end < 100% or monthly_total_amount_of_credit_transactions <= sum_loan_repayment_month | G39: Routing of funds
B40: loan repayment > 0, avg pre loan utilisation >= 80% and avg loan utilisation >= 5% | C40: -15 | D40: sum_loan_repayment_period > 0, avg_pre_loan_repayment_utilisation_period >= 80% and loan_utilisation_period >= 5% | G40: count of common records
B41: other scenarios | C41: 0 | H41: < 2 | I41: 0
H42: 2 to 5 | I42: -15
H43: > 5 | I43: -30
A45: Net cashflow movement _Tally | B45: Less than -30% | C45: -30 | G45: Related party transactions_unrelated LOB | H45: 0 to 2% | I45: 30
B46: Less than 10% | C46: -15 | H46: 2-5% | I46: 15
B47: -10 to 20% | C47: 0 | H47: 5-10% | I47: 0
B48: 21 to 50% | C48: 15 | H48: 20-10% | I48: -15
B49: more than 50% | C49: 30 | D49: avg rec = 45 | E49: credit period = 45 | H49: > 20% | I49: -30
A51: Customer Ageing | D51: 0-30 | E51: 30-60 | F51: 60-90 | G51: Product concentration | H51: <10 | I51: 30
A52: receivables % less than credit period | B52: more than 20 | C52: 30 | D52: 60 | E52: 30 | F52: 10 | H52: 10 to 15 | I52: 15
A53: receivables % less than credit period | B53: 10 to 20 | C53: 15 | H53: 15 to 20 | I53: 0
A54: receivables % less than credit period | B54: 0-10 | C54: 0 | D54: =F52/F54 -> 70 | F54: =F52/70 -> 0.14285714 | H54: 20-50 | I54: -15
A55: receivables % more than Avg receivable days of last 3 /2 /1 years | B55: 0-10 | C55: 0 | H55: >50 | I55: -30
A56: receivables % more than Avg receivable days of last 3 /2 /1 years | B56: 10 to 20 | C56: -15
A57: receivables % more than Avg receivable days of last 3 /2 /1 years | B57: more than 20 | C57: -30 | G57: Geographic concentration | H57: <10 | I57: 30
H58: 10 to 15 | I58: 15
H59: 15 to 20 | I59: 0
A60: Supplier Ageing | H60: 20-50 | I60: -15
A61: payables % less than credit period | B61: more than 20 | C61: 30 | H61: >50 | I61: -30
A62: payables % less than credit period | B62: 10 to 20 | C62: 15
A63: payables % less than credit period | B63: 0-10 | C63: 0 | G63: GST late payments
A64: payables % more than Avg payable days of last 3 /2 /1 years | B64: 0-10 | C64: 0
A65: payables % more than Avg payable days of last 3 /2 /1 years | B65: 10 to 20 | C65: -15 | H65: < 5% | I65: 0
A66: payables % more than Avg payable days of last 3 /2 /1 years | B66: more than 20 | C66: -30 | H66: 5 to 15% | I66: -15
G67: ` | H67: > 15% | I67: -30
A68: Inventory Ageing
A69: inventory % less than Avg inventory days of last 3 /2 /1 years | B69: more than 20 | C69: 30 | G69: Concentration risk - funds received from top 5 sources | H69: <10 | I69: 30
A70: inventory % less than Avg inventory days of last 3 /2 /1 years | B70: 10 to 20 | C70: 15 | H70: 10 to 15 | I70: 15
A71: inventory % less than Avg inventory days of last 3 /2 /1 years | B71: 0-10 | C71: 0 | H71: 15 to 20 | I71: 0
A72: payables % more than Avg inventory days of last 3 /2 /1 years | B72: 0-10 | C72: 0 | H72: 20-50 | I72: -15
A73: payables % more than Avg inventory days of last 3 /2 /1 years | B73: 10 to 20 | C73: -15 | H73: >50 | I73: -30
A74: payables % more than Avg inventory days of last 3 /2 /1 years | B74: more than 20 | C74: -30
G75: Concentration risk - funds remitted to top 5 | H75: <10 | I75: 30
A76: growth_annual_revenue_tally | B76: < - 10% | C76: -30
B77: - 10 to 0 | C77: -15
B78: 0 to 20 | C78: 0
B79: > 20 to 50 | C79: 15
B80: > 50 | C80: 30
A82: growth_annual_netprofit_tally | B82: < - 10% | C82: -30
B83: - 10 to 0 | C83: -15
B84: 0 to 20 | C84: 0
B85: > 20 to 50 | C85: 15
B86: > 50 | C86: 30
A88: gross sales trend_gst | B88: < - 10% | C88: -30
B89: - 10 to 0 | C89: -15
B90: 0 to 20 | C90: 0
B91: > 20 to 50 | C91: 15
B92: > 50 | C92: 30
A94: gross purchases trend_gst | B94: < - 10% | C94: -30
B95: - 10 to 0 | C95: -15
B96: 0 to 20 | C96: 0
B97: > 20 to 50 | C97: 15
B98: > 50 | C98: 30
A102: Gross profit on GST sales (GST) | B102: < - 10% | C102: -30
B103: - 10 to 0 | C103: -15
B104: 0 to 30 | C104: 0
B105: > 30 to 70 | C105: 15
B106: > 70 | C106: 30
A110: Avg cash balance change

Sheet Thresholds for Bureau
A1: commercial_bureau_score | B1: 7 to 10 | C1: -30
B2: 4 to 6 | C2: -15
B3: 3 | C3: 15
B4: 2 | C4: 30
B5: 1 | C5: 30
A7: retail_mfi_bureau_score
A13: unsecured_loans_enquiries_l30d | B13: 1 | C13: -30
B14: > 50% but not equal to 100% | C14: -15
B15: 20% to less than 50% | C15: 0
B16: >0% to 20% | C16: 15
B17: 0 | C17: 30
A19: current_account_classification_rank | B19: 1,2,3,4,5 | C19: -15
B21: 0 | C21: 15 | H21: class | I21: score
B22: 0 and historic_account_classification_rank = 0 | C22: 30 | G22: current class feature | H22: 0 | I22: =15 -> 15
G23: current class feature | H23: 1 | I23: 0
A25: historic_account_classification_rank | B25: historic_account_classification_rank = 1,2,3,4,5 | C25: -15 | E25: historic_account_classification_rank = 2,3,4,5 and current_account_classification_rank = 1,2,3,4,5 or historic_account_classification_rank = 1 and current_account_classification_rank = 2,3,4,5 | F25: -15
B26: historic_account_classification_rank = 1 or 0 and current_account_classification_rank = 0 | C26: 0 | E26: historic_account_classification_rank = 2,3,4,5 and current_account_classification_rank = 0 or historic_account_classification_rank = 1 and current_account_classification_rank = 1 | F26: -15
E27: historic_account_classification_rank = 1 and current_account_classification_rank = 0 | F27: 0

Sheet account_or_asset_classification
B1: CurrentAccountClassification | C1: Rank | D1: Bureau Overrides | E1: Final Score
B2: STD | C2: 0
B3: DPD-0 | C3: 0
B4: DPD1-30 | C4: 1
B5: SMA0 | C5: 1
B6: DPD31-60 | C6: 2 | D6: Override to C rating | E6: min of C - 0.02
B7: SMA1 | C7: 2 | D7: Override to C rating | E7: min of C - 0.02
B8: DPD61–90 | C8: 5 | D8: Override to D rating | E8: min of D - 0.01
B9: SMA2 | C9: 5 | D9: Override to D rating | E9: min of D - 0.01
B10: DPD91–180 | C10: 5 | D10: Override to D rating | E10: min of D - 0.01
B11: DPD>180 | C11: 5 | D11: Override to D rating | E11: min of D - 0.01
B12: SUB | C12: 5 | D12: Override to D rating | E12: min of D - 0.01
B13: RESTRUCTURED | C13: 4
B14: NPA | C14: 5 | D14: Override to D rating | E14: min of D - 0.01
B15: DBT | C15: 5 | D15: Override to D rating | E15: min of D - 0.01
B16: LOSS | C16: 5 | D16: Override to D rating | E16: min of D - 0.01
B17: CLOSED | C17: Ignore | D17: Ignore
B18: Others + CurrentOverdue_Amt = 0 | C18: 0
B19: Others + CurrentOverdue_Amt > 0 | C19: 1
B20: Overdue | C20: 1

Sheet Scoring - TSR PD fin UTM
C1: 0.7 | I1: =100%-C1 -> 0.3
C2: tsr score | O2: ='Scoring - fin '!O2 -> Score range | P2: ='Scoring - fin '!P2 -> Range
A3: Features_core | B3: max score cap | C3: core(70%) | D3: re arranged wights | E3: feature values-core | F3: Features_non core | G3: max score cap | H3: Non core(30%) | I3: re arranged weights | J3: feature values - non core | O3: ='Scoring - fin '!O3 -> -30 | P3: ='Scoring - fin '!P3 -> Very bad
A4: Significmant cash transactions_BS | B4: 0 | C4: 0.35 | D4: =C4/SUM(C4,C5,C6,C7,C8) -> 0.35 | E4: 0 | F4: Product concentration | G4: 0 | H4: 0.35 | I4: =H4/SUM($H$4:$H$7) -> 0.35 | J4: -30 | O4: ='Scoring - fin '!O4 -> -15 | P4: ='Scoring - fin '!P4 -> bad
A5: Customer concentration | B5: 0 | C5: 0.35 | D5: =C5/SUM(C4,C5,C6,C7,C8) -> 0.35 | E5: 0 | F5: Geographic concentration | G5: 0 | H5: 0.35 | I5: =H5/SUM($H$4:$H$7) -> 0.35 | J5: 30 | O5: ='Scoring - fin '!O5 -> 0 | P5: ='Scoring - fin '!P5 -> good
A6: Supplier concentration | B6: 0 | C6: 0.2 | D6: =C6/SUM(C4,C5,C6,C7,C8) -> 0.2 | E6: 0 | F6: Routing of funds | G6: 0 | H6: 0.25 | I6: =H6/SUM($H$4:$H$7) -> 0.25 | J6: -5 | O6: ='Scoring - fin '!O6 -> 15 | P6: ='Scoring - fin '!P6 -> v good
A7: Related party transactions_unrelated LOB | B7: 0 | C7: 0.05 | D7: =C7/SUM(C4,C5,C6,C7,C8) -> 0.05 | E7: 0 | F7: GST late payments | H7: 0.05 | I7: =H7/SUM($H$4:$H$7) -> 0.05 | J7: 30 | O7: ='Scoring - fin '!O7 -> 30 | P7: ='Scoring - fin '!P7
A8: Salary payment trend | C8: 0.05 | D8: =C8/SUM(C4,C5,C6,C7,C8) -> 0.05 | E8: 30 | J8: 30 | O8: ='Scoring - fin '!O8 | P8: ='Scoring - fin '!P8
I9: =sum(I3:I7) -> 1
C10: =sum(C4:C8) -> 1 | D10: =sum(D4:D8) -> 1
D11: Weighted score | E11: =SUMPRODUCT(D4:D8,E4:E8) -> 1.5 | J11: =SUMPRODUCT(I4:I8,J4:J8) -> 0.25 | K11: =E11*C1+J11*I1 -> 1.125 | L11: =VLOOKUP(K11,$O$3:$P$7,2,true) -> good
J13: Overall rating 5t | L13: Range per rating | N13: 18002021232
J14: 0 | K14: C | L14: =J15-J14 -> 3
J15: 3 | K15: B | L15: =J16-J15 -> 6
J16: 9 | K16: BB | L16: =J17-J16 -> 36
J17: 45 | K17: BBB | L17: =J18-J17 -> 36 | R17: 3
J18: 81 | K18: A | L18: =J19-J18 -> 11
J19: 92 | K19: AA | L19: =J20-J19 -> 4
A20: ='Scoring - fin '!A20 -> Data avail (flags) | B20: ='Scoring - fin '!B20 -> Actual value (test) Select one of data avail (flag) | C20: ='Scoring - fin '!C20 -> Fin, GST, EPF | D20: ='Scoring - fin '!D20 -> GST, EPF | E20: ='Scoring - fin '!E20 -> Fin and GST | F20: ='Scoring - fin '!F20 -> GST | G20: ='Scoring - fin '!G20 -> If period of data avail is less than 6 months (half of final) | J20: 96 | K20: AAA | L20: =J21-J20 -> 4
A21: ='Scoring - fin '!A21 -> Boost v good % | B21: =E21 -> 60 | C21: ='Scoring - fin '!C21 -> 50 | D21: ='Scoring - fin '!D21 -> 60 | E21: ='Scoring - fin '!E21 -> 60 | F21: ='Scoring - fin '!F21 -> 70 | G21: ='Scoring - fin '!G21 -> 30 | J21: 100
A22: ='Scoring - fin '!A22 -> Boost good % | B22: =E22 -> 50 | C22: ='Scoring - fin '!C22 -> 40 | D22: ='Scoring - fin '!D22 -> 50 | E22: ='Scoring - fin '!E22 -> 50 | F22: ='Scoring - fin '!F22 -> 60 | G22: ='Scoring - fin '!G22 -> 25
A23: ='Scoring - fin '!A23 -> Boost bad % | B23: =E23 -> -40 | C23: ='Scoring - fin '!C23 -> -30 | D23: ='Scoring - fin '!D23 -> -40 | E23: ='Scoring - fin '!E23 -> -40 | F23: ='Scoring - fin '!F23 -> -50 | G23: ='Scoring - fin '!G23 -> -10
A24: ='Scoring - fin '!A24 -> Boost v bad % | B24: =E24 -> -50 | C24: ='Scoring - fin '!C24 -> -40 | D24: ='Scoring - fin '!D24 -> -50 | E24: ='Scoring - fin '!E24 -> -50 | F24: ='Scoring - fin '!F24 -> -60 | G24: ='Scoring - fin '!G24 -> -25
A25: ='Scoring - fin '!A25 | B25: =C25 | C25: ='Scoring - fin '!C25 | D25: ='Scoring - fin '!D25 | E25: ='Scoring - fin '!E25 | F25: ='Scoring - fin '!F25 | G25: ='Scoring - fin '!G25
E28: =A31*0.5 -> 14 | F28: =E28*0.5 -> 7
A29: =VLOOKUP(A31,J14:K21,2,true) -> BB
A30: Final Model score | B30: Upper limits per upper rating (assuming max boost of +2 notches) | C30: Points available for movement (upward) | D30: V good | E30: Good | F30: Lower limits per lower rating (assuming max cut of -2 notches) | G30: Points available for movement (downward) | H30: Bad | I30: V Bad
A31: 28 | B31: =if($A$29=$K$14,J15,if($A$29=$K$15,J16,if($A$29=$K$16,J17,if($A$29=$K$17,J18,if($A$29=$K$18,J19,if($A$29=$K$19,J20,100)))))) -> 45 | C31: =B31-A31 -> 17 | D31: =C31*$B$21% -> 10.2 | E31: =C31*$B$22% -> 8.5 | F31: =if($A$29=$K$14,0,if($A$29=$K$15,J15,if($A$29=$K$16,J16,if($A$29=$K$17,J17,if($A$29=$K$18,J18,if($A$29=$K$19,J19,J20)))))) -> 9 | G31: =A31-F31 -> 19 | H31: =G31*$B$23% -> -7.6 | I31: =G31*$B$24% -> -9.5
A32: ='Scoring - fin '!H34 -> 4.8 | B32: =if($A$29=$K$14,J16,if($A$29=$K$15,J17,if($A$29=$K$16,J18,if($A$29=$K$17,J19,if($A$29=$K$18,J20,if($A$29=$K$19,J21,if($A$29=$K$20,0,100))))))) -> 81 | C32: =if(B32-B31<0,0,B32-B31) -> 36 | D32: =C32*$B$21% -> 21.6 | E32: =C32*$B$22% -> 18 | F32: =if($A$29=$K$14,0,if($A$29=$K$15,0,if($A$29=$K$16,J15,if($A$29=$K$17,J16,if($A$29=$K$18,J17,if($A$29=$K$19,J18,J19)))))) -> 3 | G32: =if(F31-F32<0,0,F31-F32) -> 6 | H32: =G32*$B$23% -> -2.4 | I32: =G32*$B$24% -> -3
A33: 2 | B33: =if($A$29=$K$14,J17,if($A$29=$K$15,J18,if($A$29=$K$16,J19,if($A$29=$K$17,J20,if($A$29=$K$18,J21,if($A$29=$K$19,0,if($A$29=$K$20,0,100))))))) -> 92 | C33: =if(B33-B32<0,0,B33-B32) -> 11 | D33: =C33*$B$21% -> 6.6 | E33: =C33*$B$22% -> 5.5 | F33: =if($A$29=$K$14,0,if($A$29=$K$15,0,if($A$29=$K$16,0,if($A$29=$K$17,J15,if($A$29=$K$18,J16,if($A$29=$K$19,J17,J18)))))) -> 0 | G33: =if(F32-F33<0,0,F32-F33) -> 3 | H33: =G33*$B$23% -> -1.2 | I33: =G33*$B$24% -> -1.5
A34: 2 | D34: =sum(D31:D33) -> 38.4 | E34: =sum(E31:E33) -> 32 | H34: =sum(H31:H33) -> -11.2 | I34: =sum(I31:I33) -> -14
C35: New score | D35: =D34+$A$31 -> 66.4 | E35: =E34+$A$31 -> 60 | H35: =H34+$A$31 -> 16.8 | I35: =I34+$A$31 -> 14
C36: New rating | D36: =VLOOKUP(D35,$J$14:$K$21,2,true) -> BBB | E36: =VLOOKUP(E35,$J$14:$K$21,2,true) -> BBB | H36: =VLOOKUP(H35,$J$14:$K$21,2,true) -> BB | I36: =VLOOKUP(I35,$J$14:$K$21,2,true) -> BB
C37: Diff score | D37: =D35-$A$31 -> 38.4 | E37: =E35-$A$31 -> 32 | H37: =H35-$A$31 -> -11.2 | I37: =I35-$A$31 -> -14
C38: Diff % | D38: =D37/$A$31 -> 1.3714286 | E38: =E37/$A$31 -> 1.1428571 | H38: =H37/$A$31 -> -0.4 | I38: =I37/$A$31 -> -0.5

Sheet total_credit_to_loans_repaid_BS
A1: Financial Consent Feature | B1: Thresholds | C1: Scores | D1: Center point | H1: Month | I1: Monthly score
A2: total_credit_to_loans_repaid_BSA_tally | B2: less than 0.75 | C2: -30 | D2: =AVERAGE(C2:C3) -> -22.5 | H2: 1 | I2: -30
B3: 0.75 to 1 | C3: -15 | D3: =AVERAGE(C3:C4) -> -7.5 | H3: 2 | I3: 0
B4: 1 to 1.5 | C4: 0 | D4: =AVERAGE(C4:C5) -> 7.5 | H4: 3 | I4: 0
B5: 1.5 to 2 | C5: 15 | D5: =AVERAGE(C5:C6) -> 22.5 | H5: 4 | I5: 0
B6: more than 2 | C6: 30 | H6: 5 | I6: 15
H7: 6 | I7: 15
H8: 7 | I8: 15
B9: overutilisation | C9: -30 | H9: 8 | I9: 15
A10: contribution in utilisation | B10: > =3 | C10: -15 | H10: 9 | I10: 15
B11: 1 to 2 | C11: 0 | H11: 10 | I11: 15
B12: 0 to 0.5 | C12: 15 | H12: 11 | I12: 15
B13: < 0 | C13: 30 | H13: 12 | I13: 15
H14: sum l6m | I14: =sum(I8:I13) -> 90
H15: sum ltm - l6m | I15: =sum(I2:I13)-I14 -> 0
B16: 80 | H16: final computed score | I16: =((I14/6)*70%)+((I15/6)*30%) -> 10.5
B17: 82 | H17: final score to model | I17: =if(and(I16>D2,I16<D3),C3,if(and(I16>D3,I16<D4),C4,if(and(I16>D4,I16<D5),C5,if(and(I16>D5,I16<D6),C6,C2)))) -> 15

Sheet customer ageing
F1: cp | G1: avg cred | I1: 0-30 | J1: 30-60 | K1: 60-90 | L1: 90-180 | M1: > 180
B2: days | C2: value | F2: 33 | G2: 60 | I2: =SUM(C3:C5) -> 94 | J2: =SUM(C6:C7) -> 133 | K2: =SUM(C9,C11) -> 158 | L2: =SUM(C8) -> 97 | M2: =C10 -> 182 | N2: =SUM(I2:M2) -> 664
A3: a | B3: 30 | C3: 30 | D3: =SUM(C3:C5) -> 94 | E3: =D3/C12 -> 0.14156627 | I3: =I2/$N$2 -> 0.14156627 | J3: =J2/$N$2 -> 0.2003012 | K3: =K2/$N$2 -> 0.23795181 | L3: =L2/$N$2 -> 0.14608434 | M3: =M2/$N$2 -> 0.27409639
A4: b | B4: 33 | C4: 33 | I4: =I3 -> 0.14156627 | J4: =J3 -> 0.2003012 | K4: =K3*2 -> 0.47590361 | L4: =L3*3 -> 0.43825301 | M4: =M3*4 -> 1.0963855
A5: c | B5: 31 | C5: 31 | I5: =I4/SUM($I$4:$M$4) -> 0.060179257 | J5: =J4/SUM($I$4:$M$4) -> 0.085147247 | K5: =K4/SUM($I$4:$M$4) -> 0.20230474 | L5: =L4/SUM($I$4:$M$4) -> 0.18629962 | M5: =M4/SUM($I$4:$M$4) -> 0.46606914
A6: d | B6: 66 | C6: 66 | D6: =SUM(C6:C11) -> 570 | E6: =D6/C12 -> 0.85843373
A7: e | B7: 67 | C7: 67
A8: f | B8: 97 | C8: 97
A9: g | B9: 80 | C9: 80
A10: h | B10: 182 | C10: 182 | I10: 30 | J10: 15 | K10: 0 | L10: -15 | M10: -30
A11: i | B11: 78 | C11: 78 | N11: =SUMPRODUCT(I5:M5,I10:M10) -> -13.693982 | O11: =SUMPRODUCT(I3:M3,I10:M10) -> -3.1626506
C12: =SUM(C3:C11) -> 664
F15: cp | G15: avg cred | I15: 0-30 | J15: 30-60 | K15: 60-90 | L15: 90-180 | M15: > 180
B16: days | C16: value | F16: 33 | G16: 60 | I16: =SUM(C17:C19) -> 300 | J16: =SUM(C20:C21) -> 133 | K16: =SUM(C23,C25) -> 90 | L16: =SUM(C22) -> 10 | M16: =C24 -> 10 | N16: =SUM(I16:M16) -> 543
A17: a | B17: 30 | C17: 100 | D17: =SUM(C17:C19) -> 300 | E17: =D17/C26 -> 0.55248619 | I17: =I16/$N$16 -> 0.55248619 | J17: =J16/$N$16 -> 0.24493554 | K17: =K16/$N$16 -> 0.16574586 | L17: =L16/$N$16 -> 0.018416206 | M17: =M16/$N$16 -> 0.018416206
A18: b | B18: 33 | C18: 100 | I18: =I17 -> 0.55248619 | J18: =J17 -> 0.24493554 | K18: =K17*2 -> 0.33149171 | L18: =L17*3 -> 0.055248619 | M18: =M17*4 -> 0.073664825
A19: c | B19: 31 | C19: 100 | I19: =I18/SUM($I$18:$M$18) -> 0.43923865 | J19: =J18/SUM($I$18:$M$18) -> 0.19472914 | K19: =K18/SUM($I$18:$M$18) -> 0.26354319 | L19: =L18/SUM($I$18:$M$18) -> 0.043923865 | M19: =M18/SUM($I$18:$M$18) -> 0.058565154
A20: d | B20: 66 | C20: 66 | D20: =SUM(C20:C25) -> 243 | E20: =D20/C26 -> 0.44751381
A21: e | B21: 67 | C21: 67
A22: f | B22: 97 | C22: 10
A23: g | B23: 80 | C23: 80
A24: h | B24: 182 | C24: 10 | I24: 30 | J24: 15 | K24: 0 | L24: -15 | M24: -30
A25: i | B25: 78 | C25: 10 | N25: =SUMPRODUCT(I19:M19,I24:M24) -> 13.682284 | O25: =SUMPRODUCT(I17:M17,I24:M24) -> 19.41989
C26: =SUM(C17:C25) -> 543

Sheet Scoring - TSR PD fin Experiment
C1: 0.9 | J1: 0.1
C2: tsr score | P2: ='Scoring - fin '!O2 -> Score range | Q2: ='Scoring - fin '!P2 -> Range
A3: Features_core | B3: max score cap | C3: core(70%) | D3: re arranged wights | E3: feature values-core | G3: Features_non core | H3: max score cap | I3: Non core(30%) | J3: re arranged weights | K3: feature values - non core | P3: ='Scoring - fin '!O3 -> -30 | Q3: ='Scoring - fin '!P3 -> Very bad
A4: Significant_cash_transactions_amount_BSA_tally | B4: 0 | C4: 0.15 | D4: =C4/SUM($C$4,$C$5,$C$6,$C$7,$C$8,$C$9) -> 0.375 | E4: 15 | G4: Related_party_transactions_unrelated_LOB_ITR_Tally_BS_GST | H4: 0 | I4: 0 | J4: =I4/SUM($I$4:$I$9) -> 0 | K4: 0 | P4: ='Scoring - fin '!O4 -> -15 | Q4: ='Scoring - fin '!P4 -> bad
A5: Significant_cash_transactions_count_BSA_tally | B5: 0 | C5: 0.15 | D5: =C5/SUM($C$4,$C$5,$C$6,$C$7,$C$8,$C$9) -> 0.375 | E5: -15 | G5: product_concentration_Tally_gst | H5: 0 | I5: 0 | J5: =I5/SUM($I$4:$I$9) -> 0 | K5: 0 | P5: ='Scoring - fin '!O5 -> 0 | Q5: ='Scoring - fin '!P5 -> good
A6: customer_concentration_GST_Tally | B6: 0 | C6: 0 | D6: =C6/SUM($C$4,$C$5,$C$6,$C$7,$C$8,$C$9) -> 0 | G6: geographic_concentration_GST | H6: 0 | I6: 0 | J6: =I6/SUM($I$4:$I$9) -> 0 | K6: 0 | P6: ='Scoring - fin '!O6 -> 15 | Q6: ='Scoring - fin '!P6 -> v good
A7: supplier_concentration_GST_Tally | B7: 0 | C7: 0 | D7: =C7/SUM($C$4,$C$5,$C$6,$C$7,$C$8,$C$9) -> 0 | G7: late_payment_fees_GST_Tally | I7: 0 | J7: =I7/SUM($I$4:$I$9) -> 0 | K7: 0 | P7: ='Scoring - fin '!O7 -> 30 | Q7: ='Scoring - fin '!P7
A8: salary_payment_delay_Tally_BSA | C8: 0 | D8: =C8/SUM($C$4,$C$5,$C$6,$C$7,$C$8,$C$9) -> 0 | E8: 0 | G8: concentration_risk_funds received_from_top_5_sources_BS | I8: 0.05 | J8: =I8/SUM($I$4:$I$9) -> 0.5 | K8: -30 | P8: ='Scoring - fin '!O8 | Q8: ='Scoring - fin '!P8
A9: routing_of_funds_BSA_tally | C9: 0.1 | D9: =C9/SUM($C$4,$C$5,$C$6,$C$7,$C$8,$C$9) -> 0.25 | E9: -15 | G9: concentration_risk_funds remitted_to_top_5_sources_BS | I9: 0.05 | J9: =I9/SUM($I$4:$I$9) -> 0.5 | K9: -15
C10: =sum(C4:C9) -> 0.4 | D10: =sum(D4:D9) -> 1 | I10: =SUM(I4:I9) -> 0.1 | J10: =SUM(J4:J9) -> 1 | S10: 1 | T10: 2 | U10: 3 | V10: 4
D11: Weighted score | E11: =SUMPRODUCT(D4:D9,E4:E9) -> -3.75 | K11: =SUMPRODUCT(J4:J9,K4:K9) -> -22.5 | L11: =E11*C1+K11*J1 -> -5.625 | M11: =VLOOKUP(L11,$P$3:$Q$7,2,true) -> bad
F12: Count of non core available | G12: Weightage non core | H12: Weightage core
F13: 0-2 | G13: 10 | H13: 90 | K13: Overall rating 5t | M13: Range per rating | O13: 18002021232
F14: 44624 | G14: 20 | H14: 80 | K14: 0 | L14: C | M14: =K15-K14 -> 3
F15: >=5 | G15: 30 | H15: 70 | K15: 3 | L15: B | M15: =K16-K15 -> 6
K16: 9 | L16: BB | M16: =K17-K16 -> 36
K17: 45 | L17: BBB | M17: =K18-K17 -> 36 | S17: 3
K18: 81 | L18: A | M18: =J19-K18 -> -81
K19: 92 | L19: AA
A20: ='Scoring - fin '!A20 -> Data avail (flags) | B20: ='Scoring - fin '!B20 -> Actual value (test) Select one of data avail (flag) | C20: ='Scoring - fin '!C20 -> Fin, GST, EPF | D20: ='Scoring - fin '!D20 -> GST, EPF | E20: ='Scoring - fin '!E20 -> Fin and GST | F20: ='Scoring - fin '!F20 -> GST | G20: ='Scoring - fin '!G20 -> If period of data avail is less than 6 months (half of final) | K20: 96 | L20: AAA
A21: ='Scoring - fin '!A21 -> Boost v good % | B21: =C21 -> 50 | C21: ='Scoring - fin '!C21 -> 50 | D21: ='Scoring - fin '!D21 -> 60 | E21: ='Scoring - fin '!E21 -> 60 | F21: ='Scoring - fin '!F21 -> 70 | G21: ='Scoring - fin '!G21 -> 30 | K21: 100
A22: ='Scoring - fin '!A22 -> Boost good % | B22: =C22 -> 40 | C22: ='Scoring - fin '!C22 -> 40 | D22: ='Scoring - fin '!D22 -> 50 | E22: ='Scoring - fin '!E22 -> 50 | F22: ='Scoring - fin '!F22 -> 60 | G22: ='Scoring - fin '!G22 -> 25
A23: ='Scoring - fin '!A23 -> Boost bad % | B23: =C23 -> -30 | C23: ='Scoring - fin '!C23 -> -30 | D23: ='Scoring - fin '!D23 -> -40 | E23: ='Scoring - fin '!E23 -> -40 | F23: ='Scoring - fin '!F23 -> -50 | G23: ='Scoring - fin '!G23 -> -10
A24: ='Scoring - fin '!A24 -> Boost v bad % | B24: =C24 -> -40 | C24: ='Scoring - fin '!C24 -> -40 | D24: ='Scoring - fin '!D24 -> -50 | E24: ='Scoring - fin '!E24 -> -50 | F24: ='Scoring - fin '!F24 -> -60 | G24: ='Scoring - fin '!G24 -> -25
A25: ='Scoring - fin '!A25 | B25: =C25 | C25: ='Scoring - fin '!C25 | D25: ='Scoring - fin '!D25 | E25: ='Scoring - fin '!E25 | F25: ='Scoring - fin '!F25 | G25: ='Scoring - fin '!G25
A29: =VLOOKUP(A31,K14:L21,2,true) -> BB
A30: TSR Model score | B30: Upper limits per upper rating (assuming max boost of +2 notches) | C30: Points available for movement (upward) | D30: V good | E30: Good | F30: Lower limits per lower rating (assuming max cut of -2 notches) | G30: Points available for movement (downward) | H30: Bad | I30: V Bad
A31: 13 | B31: =if($A$29=$L$14,K15,if($A$29=$L$15,K16,if($A$29=$L$16,K17,if($A$29=$L$17,K18,if($A$29=$L$18,J19,if($A$29=$K$19,J20,100)))))) -> 45 | C31: =B31-A31 -> 32 | D31: =C31*$B$21% -> 16 | E31: =C31*$B$22% -> 12.8 | F31: =if($A$29=$L$14,0,if($A$29=$L$15,K15,if($A$29=$L$16,K16,if($A$29=$L$17,K17,if($A$29=$L$18,K18,if($A$29=$K$19,J19,J20)))))) -> 9 | G31: =A31-F31 -> 4 | H31: =G31*$B$23% -> -1.2 | I31: =G31*$B$24% -> -1.6
B32: =if($A$29=$L$14,K16,if($A$29=$L$15,K17,if($A$29=$L$16,K18,if($A$29=$L$17,J19,if($A$29=$L$18,J20,if($A$29=$K$19,J21,if($A$29=$K$20,0,100))))))) -> 81 | C32: =if(B32-B31<0,0,B32-B31) -> 36 | D32: =C32*$B$21% -> 18 | E32: =C32*$B$22% -> 14.4 | F32: =if($A$29=$L$14,0,if($A$29=$L$15,0,if($A$29=$L$16,K15,if($A$29=$L$17,K16,if($A$29=$L$18,K17,if($A$29=$K$19,K18,J19)))))) -> 3 | G32: =if(F31-F32<0,0,F31-F32) -> 6 | H32: =G32*$B$23% -> -1.8 | I32: =G32*$B$24% -> -2.4
B33: =if($A$29=$L$14,K17,if($A$29=$L$15,K18,if($A$29=$L$16,J19,if($A$29=$L$17,J20,if($A$29=$L$18,J21,if($A$29=$K$19,0,if($A$29=$K$20,0,100))))))) | C33: =if(B33-B32<0,0,B33-B32) -> 0 | D33: =C33*$B$21% -> 0 | E33: =C33*$B$22% -> 0 | F33: =if($A$29=$L$14,0,if($A$29=$L$15,0,if($A$29=$L$16,0,if($A$29=$L$17,K15,if($A$29=$L$18,K16,if($A$29=$K$19,K17,K18)))))) -> 0 | G33: =if(F32-F33<0,0,F32-F33) -> 3 | H33: =G33*$B$23% -> -0.9 | I33: =G33*$B$24% -> -1.2
D34: =sum(D31:D33) -> 34 | E34: =sum(E31:E33) -> 27.2 | H34: =sum(H31:H33) -> -3.9 | I34: =sum(I31:I33) -> -5.2
C35: New score | D35: =D34+$A$31 -> 47 | E35: =E34+$A$31 -> 40.2 | H35: =H34+$A$31 -> 9.1 | I35: =I34+$A$31 -> 7.8
C36: New rating | D36: =VLOOKUP(D35,$K$14:$L$21,2,true) -> BBB | E36: =VLOOKUP(E35,$K$14:$L$21,2,true) -> BB | H36: =VLOOKUP(H35,$K$14:$L$21,2,true) -> BB | I36: =VLOOKUP(I35,$K$14:$L$21,2,true) -> B
C37: Diff score | D37: =D35-$A$31 -> 34 | E37: =E35-$A$31 -> 27.2 | H37: =H35-$A$31 -> -3.9 | I37: =I35-$A$31 -> -5.2
C38: Diff % | D38: =D37/$A$31 -> 2.6153846 | E38: =E37/$A$31 -> 2.0923077 | H38: =H37/$A$31 -> -0.3 | I38: =I37/$A$31 -> -0.4

Sheet Sheet25
C1: 0.9 | J1: 0.1
C2: tsr score | P2: ='Scoring - fin '!O2 -> Score range | Q2: ='Scoring - fin '!P2 -> Range
A3: Features_core | B3: max score cap | C3: core(70%) | D3: re arranged wights | E3: feature values-core | G3: Features_non core | H3: max score cap | I3: Non core(30%) | J3: re arranged weights | K3: feature values - non core | P3: ='Scoring - fin '!O3 -> -30 | Q3: ='Scoring - fin '!P3 -> Very bad
A4: Significant_cash_transactions_amount_BSA_tally | B4: 0 | C4: 0.15 | D4: =C4/SUM($C$4,$C$5,$C$6,$C$7,$C$8,$C$9) -> 0.375 | E4: 15 | G4: Related_party_transactions_unrelated_LOB_ITR_Tally_BS_GST | H4: 0 | I4: 0 | J4: =I4/SUM($I$4:$I$9) -> 0 | K4: 0 | P4: ='Scoring - fin '!O4 -> -15 | Q4: ='Scoring - fin '!P4 -> bad
A5: Significant_cash_transactions_count_BSA_tally | B5: 0 | C5: 0.15 | D5: =C5/SUM($C$4,$C$5,$C$6,$C$7,$C$8,$C$9) -> 0.375 | E5: 0 | G5: product_concentration_Tally_gst | H5: 0 | I5: 0 | J5: =I5/SUM($I$4:$I$9) -> 0 | K5: 0 | P5: ='Scoring - fin '!O5 -> 0 | Q5: ='Scoring - fin '!P5 -> good
A6: customer_concentration_GST_Tally | B6: 0 | C6: 0 | D6: =C6/SUM($C$4,$C$5,$C$6,$C$7,$C$8,$C$9) -> 0 | G6: geographic_concentration_GST | H6: 0 | I6: 0 | J6: =I6/SUM($I$4:$I$9) -> 0 | K6: 0 | P6: ='Scoring - fin '!O6 -> 15 | Q6: ='Scoring - fin '!P6 -> v good
A7: supplier_concentration_GST_Tally | B7: 0 | C7: 0 | D7: =C7/SUM($C$4,$C$5,$C$6,$C$7,$C$8,$C$9) -> 0 | G7: late_payment_fees_GST_Tally | I7: 0 | J7: =I7/SUM($I$4:$I$9) -> 0 | K7: 0 | P7: ='Scoring - fin '!O7 -> 30 | Q7: ='Scoring - fin '!P7
A8: salary_payment_delay_Tally_BSA | C8: 0 | D8: =C8/SUM($C$4,$C$5,$C$6,$C$7,$C$8,$C$9) -> 0 | E8: 0 | G8: concentration_risk_funds received_from_top_5_sources_BS | I8: 0.05 | J8: =I8/SUM($I$4:$I$9) -> 0.5 | K8: -30 | P8: ='Scoring - fin '!O8 | Q8: ='Scoring - fin '!P8
A9: routing_of_funds_BSA_tally | C9: 0.1 | D9: =C9/SUM($C$4,$C$5,$C$6,$C$7,$C$8,$C$9) -> 0.25 | E9: -15 | G9: concentration_risk_funds remitted_to_top_5_sources_BS | I9: 0.05 | J9: =I9/SUM($I$4:$I$9) -> 0.5 | K9: -15
C10: =sum(C4:C9) -> 0.4 | D10: =sum(D4:D9) -> 1 | I10: =SUM(I4:I9) -> 0.1 | J10: =SUM(J4:J9) -> 1 | S10: 1 | T10: 2 | U10: 3 | V10: 4
D11: Weighted score | E11: =SUMPRODUCT(D4:D9,E4:E9) -> 1.875 | K11: =SUMPRODUCT(J4:J9,K4:K9) -> -22.5 | L11: =E11*C1+K11*J1 -> -0.5625 | M11: =VLOOKUP(L11,$P$3:$Q$7,2,true) -> bad
F13: 0-2 | G13: 10 | K13: Overall rating 5t | M13: Range per rating | O13: 18002021232
F14: 44624 | G14: 20 | K14: 0 | L14: C | M14: =K15-K14 -> 3
F15: 44687 | G15: 30 | K15: 3 | L15: B | M15: =K16-K15 -> 6
K16: 9 | L16: BB | M16: =K17-K16 -> 36
K17: 45 | L17: BBB | M17: =K18-K17 -> 36 | S17: 3
K18: 81 | L18: A | M18: =J19-K18 -> -81
K19: 92 | L19: AA
A20: ='Scoring - fin '!A20 -> Data avail (flags) | B20: ='Scoring - fin '!B20 -> Actual value (test) Select one of data avail (flag) | C20: ='Scoring - fin '!C20 -> Fin, GST, EPF | D20: ='Scoring - fin '!D20 -> GST, EPF | E20: ='Scoring - fin '!E20 -> Fin and GST | F20: ='Scoring - fin '!F20 -> GST | G20: ='Scoring - fin '!G20 -> If period of data avail is less than 6 months (half of final) | K20: 96 | L20: AAA
A21: ='Scoring - fin '!A21 -> Boost v good % | B21: =G21 -> 30 | C21: ='Scoring - fin '!C21 -> 50 | D21: ='Scoring - fin '!D21 -> 60 | E21: ='Scoring - fin '!E21 -> 60 | F21: ='Scoring - fin '!F21 -> 70 | G21: =E21/2 -> 30 | K21: 100
A22: ='Scoring - fin '!A22 -> Boost good % | B22: =G22 -> 25 | C22: ='Scoring - fin '!C22 -> 40 | D22: ='Scoring - fin '!D22 -> 50 | E22: ='Scoring - fin '!E22 -> 50 | F22: ='Scoring - fin '!F22 -> 60 | G22: =E22/2 -> 25
A23: ='Scoring - fin '!A23 -> Boost bad % | B23: =G23 -> -20 | C23: ='Scoring - fin '!C23 -> -30 | D23: ='Scoring - fin '!D23 -> -40 | E23: ='Scoring - fin '!E23 -> -40 | F23: ='Scoring - fin '!F23 -> -50 | G23: =E23/2 -> -20
A24: ='Scoring - fin '!A24 -> Boost v bad % | B24: =G24 -> -25 | C24: ='Scoring - fin '!C24 -> -40 | D24: ='Scoring - fin '!D24 -> -50 | E24: ='Scoring - fin '!E24 -> -50 | F24: ='Scoring - fin '!F24 -> -60 | G24: =E24/2 -> -25
A25: ='Scoring - fin '!A25 | B25: =G25 -> 0 | C25: ='Scoring - fin '!C25 | D25: ='Scoring - fin '!D25 | E25: ='Scoring - fin '!E25 | F25: ='Scoring - fin '!F25 | G25: =E25/2 -> 0
A29: =VLOOKUP(A31,K14:L21,2,true) -> BBB
A30: TSR Model score | B30: Upper limits per upper rating (assuming max boost of +2 notches) | C30: Points available for movement (upward) | D30: V good | E30: Good | F30: Lower limits per lower rating (assuming max cut of -2 notches) | G30: Points available for movement (downward) | H30: Bad | I30: V Bad
A31: 51 | B31: =if($A$29=$L$14,K15,if($A$29=$L$15,K16,if($A$29=$L$16,K17,if($A$29=$L$17,K18,if($A$29=$L$18,J19,if($A$29=$K$19,J20,100)))))) -> 81 | C31: =B31-A31 -> 30 | D31: =C31*$B$21% -> 9 | E31: =C31*$B$22% -> 7.5 | F31: =if($A$29=$L$14,0,if($A$29=$L$15,K15,if($A$29=$L$16,K16,if($A$29=$L$17,K17,if($A$29=$L$18,K18,if($A$29=$K$19,J19,J20)))))) -> 45 | G31: =A31-F31 -> 6 | H31: =G31*$B$23% -> -1.2 | I31: =G31*$B$24% -> -1.5
B32: =if($A$29=$L$14,K16,if($A$29=$L$15,K17,if($A$29=$L$16,K18,if($A$29=$L$17,J19,if($A$29=$L$18,J20,if($A$29=$K$19,J21,if($A$29=$K$20,0,100))))))) | C32: =if(B32-B31<0,0,B32-B31) -> 0 | D32: =C32*$B$21% -> 0 | E32: =C32*$B$22% -> 0 | F32: =if($A$29=$L$14,0,if($A$29=$L$15,0,if($A$29=$L$16,K15,if($A$29=$L$17,K16,if($A$29=$L$18,K17,if($A$29=$K$19,K18,J19)))))) -> 9 | G32: =if(F31-F32<0,0,F31-F32) -> 36 | H32: =G32*$B$23% -> -7.2 | I32: =G32*$B$24% -> -9
B33: =if($A$29=$L$14,K17,if($A$29=$L$15,K18,if($A$29=$L$16,J19,if($A$29=$L$17,J20,if($A$29=$L$18,J21,if($A$29=$K$19,0,if($A$29=$K$20,0,100))))))) | C33: =if(B33-B32<0,0,B33-B32) -> 0 | D33: =C33*$B$21% -> 0 | E33: =C33*$B$22% -> 0 | F33: =if($A$29=$L$14,0,if($A$29=$L$15,0,if($A$29=$L$16,0,if($A$29=$L$17,K15,if($A$29=$L$18,K16,if($A$29=$K$19,K17,K18)))))) -> 3 | G33: =if(F32-F33<0,0,F32-F33) -> 6 | H33: =G33*$B$23% -> -1.2 | I33: =G33*$B$24% -> -1.5
D34: =sum(D31:D33) -> 9 | E34: =sum(E31:E33) -> 7.5 | H34: =sum(H31:H33) -> -9.6 | I34: =sum(I31:I33) -> -12
C35: New score | D35: =D34+$A$31 -> 60 | E35: =E34+$A$31 -> 58.5 | H35: =H34+$A$31 -> 41.4 | I35: =I34+$A$31 -> 39
C36: New rating | D36: =VLOOKUP(D35,$K$14:$L$21,2,true) -> BBB | E36: =VLOOKUP(E35,$K$14:$L$21,2,true) -> BBB | H36: =VLOOKUP(H35,$K$14:$L$21,2,true) -> BB | I36: =VLOOKUP(I35,$K$14:$L$21,2,true) -> BB
C37: Diff score | D37: =D35-$A$31 -> 9 | E37: =E35-$A$31 -> 7.5 | H37: =H35-$A$31 -> -9.6 | I37: =I35-$A$31 -> -12
C38: Diff % | D38: =D37/$A$31 -> 0.17647059 | E38: =E37/$A$31 -> 0.14705882 | H38: =H37/$A$31 -> -0.18823529 | I38: =I37/$A$31 -> -0.23529412

Sheet Scoring - fin experiment SCPL
C1: 0.9 | J1: 0.1
C2: fin score | O2: Score range | P2: Range
A3: Features_core | B3: max score cap | C3: core(70%) | D3: re arranged weights | E3: feature values-core | G3: Features_non core | H3: max score cap | I3: Non core(30%) | J3: re arranged weights | K3: feature values - non core | N3: 0 | O3: -30 | P3: Very bad | Q3: red
A4: wc_utilisation_ltm_BSA_Tally | B4: 0 | C4: 20 | D4: =C4/SUM(C4,C5,C6,C7,C8,C9,C10) -> 0.2 | E4: -15 | G4: net_cashflow_movement _tally_BSA | H4: 0 | J4: =I4/SUM($I$4:$I$10) -> #DIV/0! | K4: 0 | O4: -15 | P4: bad | Q4: brownish
A5: wc_utilisation_l6m_BSA_Tally | C5: 10 | D5: =C5/SUM(C4,C5,C6,C7,C8,C9,C10) -> 0.1 | E5: -15 | G5: customer_ageing_tally | J5: =I5/SUM($I$4:$I$10) -> #DIV/0! | K5: 0 | O5: 0 | P5: good | Q5: light green
A6: effective_interest_rate_BSA_Tally | C6: 20 | D6: =C6/SUM(C4,C5,C6,C7,C8,C9,C10) -> 0.2 | E6: -15 | G6: supplier_ageing_tally | J6: =I6/SUM($I$4:$I$10) -> #DIV/0! | K6: 0 | O6: 15 | P6: v good | Q6: gree
A7: churn_rate_BSA_tally | B7: 0 | C7: 20 | D7: =C7/SUM(C4,C5,C6,C7,C8,C9,C10) -> 0.2 | E7: 0 | G7: inventory_ageing_tally | J7: =I7/SUM($I$4:$I$10) -> #DIV/0! | K7: 0 | O7: 30
A8: Inward cheque returns_BSA_tally | C8: 10 | D8: =C8/SUM(C4,C5,C6,C7,C8,C9,C10) -> 0.1 | E8: 30 | G8: gross_profit_on_sales_GST_Tally | J8: =I8/SUM($I$4:$I$10) -> #DIV/0! | K8: 0 | N8: 100 | O8: 30
A9: overutilisation_frequency_BSA_Tally | C9: 10 | D9: =C9/SUM(C4,C5,C6,C7,C8,C9,C10) -> 0.1 | E9: -30 | G9: avg_cash_balance_change_tally | J9: =I9/SUM($I$4:$I$10) -> #DIV/0! | K9: 0
A10: pre_post_loan_utilisation_BSA_tally | C10: 10 | D10: =C10/SUM(C4,C5,C6,C7,C8,C9,C10) -> 0.1 | E10: -30 | G10: gross_sales_trend_gst_tally | J10: =I10/SUM($I$4:$I$10) -> #DIV/0! | K10: 0
C11: =sum(C4:C10) -> 100 | D11: =sum(D4:D10) -> 1 | I11: =sum(I4:I10) -> 0 | J11: =sum(J4:J10) -> #DIV/0! | R11: 1 | S11: 2 | T11: 3 | U11: 4
D12: Weighted score | E12: =SUMPRODUCT(D4:D10,E4:E10) -> -10.5 | K12: =SUMPRODUCT(J4:J10,K4:K10) -> #DIV/0! | L12: =E12*C1 -> -9.45 | M12: =VLOOKUP(L12,$O$3:$P$8,2,true) -> bad
E14: Count of non core available | F14: Weightage | J14: Overall rating 5t | L14: Range per rating
E15: 0-2 | F15: 10 | J15: 0 | K15: C | L15: =J16-J15 -> 3
E16: 44624 | F16: 20 | J16: 3 | K16: B | L16: =J17-J16 -> 6
E17: >=5 | F17: 30 | J17: 9 | K17: BB | L17: =J18-J17 -> 36
J18: 45 | K18: BBB | L18: =J19-J18 -> 36 | R18: 3
J19: 81 | K19: A | L19: =J20-J19 -> 11
J20: 92 | K20: AA | L20: =J21-J20 -> 4
A21: Data avail (flags) | B21: Actual value (test) Select one of data avail (flag) | C21: Fin, GST, EPF | D21: GST, EPF | E21: Fin and GST | F21: GST | G21: If period of data avail is less than 6 months (half of final) | J21: 96 | K21: AAA | L21: =J22-J21 -> 4
A22: Boost v good % | B22: =C22 -> 50 | C22: 50 | D22: =C22+5 -> 55 | E22: 60 | F22: =C22+20 -> 70 | G22: =B22/2 -> 25 | J22: 100
A23: Boost good % | B23: =C23 -> 40 | C23: 40 | D23: =C23+5 -> 45 | E23: 50 | F23: =C23+20 -> 60 | G23: =B23/2 -> 20
A24: Boost bad % | B24: =C24 -> -30 | C24: =-C23+10 -> -30 | D24: =C24+5 -> -25 | E24: =-E23+10 -> -40 | F24: =C24+20 -> -10 | G24: =B24/2 -> -15
A25: Boost v bad % | B25: =C25 -> -40 | C25: =-C22+10 -> -40 | D25: =C25+5 -> -35 | E25: =-E22+10 -> -50 | F25: =C25+20 -> -20 | G25: =B25/2 -> -20
A26: Boost avg | B26: =C26 -> 20 | C26: =C23/2 -> 20 | D26: =D23/2 -> 22.5 | E26: =E23/2 -> 25 | F26: =F23/2 -> 30 | G26: =G23/2 -> 10
A30: When only GST AV | H30: When FIN and GST AV | J30: When GST EPFO AV | N30: When FIN GST EPFO AV
A31: consent score | B31: Fin | C31: GST | D31: EPFO | E31: Original TSR | F31: TSR consent | H31: consent score | I31: Fin | J31: GST | K31: EPFO | M31: TSR | O31: consent score | P31: Fin | Q31: GST | R31: EPFO | T31: TSR
B32: 0.35 | C32: 2 | D32: 2 | F32: 0.46 | I32: 0.35 | J32: 2 | K32: 2 | M32: 0.46 | P32: 0.35 | Q32: 2 | R32: 2 | T32: 0.46
A33: vgood | B33: 0.749 | C33: 2 | D33: 2 | E33: 0.818 | F33: 0.946 | H33: vgood | I33: 0.692 | J33: 2 | K33: 2 | L33: 0.781 | M33: 0.888 | O33: vgood | P33: 0.635 | Q33: 2 | R33: 2 | S33: 0.737 | T33: 0.8485
A34: good | B34: 0.692 | C34: 2 | D34: 2 | E34: 0.781 | F34: 0.888 | H34: good | I34: 0.635 | J34: 2 | K34: 2 | L34: 0.737 | M34: 0.848 | O34: good | P34: 0.578 | Q34: 2 | R34: 2 | S34: 0.689 | T34: 0.797
A35: avg | B35: 0.521 | C35: 2 | D35: 2 | E35: 0.636 | H35: avg | I35: 0.4925 | J35: 2 | K35: 2 | L35: 0.608 | O35: avg | P35: 0.464 | Q35: 2 | R35: 2 | S35: 0.58
A36: bad | B36: 0.175 | C36: 2 | D36: 2 | E36: 0.294 | F36: 0.147 | H36: bad | I36: 0.21 | J36: 2 | K36: 2 | L36: 0.326 | M36: 0.195 | O36: bad | P36: 0.245 | Q36: 2 | R36: 2 | S36: 0.35 | T36: 0.245
A37: vbad | B37: 0.14 | C37: 2 | D37: 2 | E37: 0.265 | F37: 0.106 | H37: vbad | I37: 0.175 | J37: 2 | K37: 2 | L37: 0.294 | M37: 0.875 | O37: vbad | P37: 0.21 | Q37: 2 | R37: 2 | S37: 0.326 | T37: 0.195
A39: =VLOOKUP(A41,J15:K22,2,true) -> BB
A40: Fin Model score | B40: Upper limits per upper rating (assuming max boost of +2 notches) | C40: Points available for movement (upward) | D40: V good | E40: Good | F40: Avg | G40: Lower limits per lower rating (assuming max cut of -2 notches) | H40: Points available for movement (downward) | I40: Bad | J40: V Bad
A41: 21 | B41: =if($A$39=$K$15,J16,if($A$39=$K$16,J17,if($A$39=$K$17,J18,if($A$39=$K$18,J19,if($A$39=$K$19,J20,if($A$39=$K$20,J21,100)))))) -> 45 | C41: =B41-A41 -> 24 | D41: =C41*$B$22% -> 12 | E41: =C41*$B$23% -> 9.6 | F41: =C41*$B$26% -> 4.8 | G41: =if($A$39=$K$15,0,if($A$39=$K$16,J16,if($A$39=$K$17,J17,if($A$39=$K$18,J18,if($A$39=$K$19,J19,if($A$39=$K$20,J20,J21)))))) -> 9 | H41: =A41-G41 -> 12 | I41: =H41*$B$24% -> -3.6 | J41: =H41*$B$25% -> -4.8
B42: =if($A$39=$K$15,J17,if($A$39=$K$16,J18,if($A$39=$K$17,J19,if($A$39=$K$18,J20,if($A$39=$K$19,J21,if($A$39=$K$20,J22,if($A$39=$K$21,0,100))))))) -> 81 | C42: =if(B42-B41<0,0,B42-B41) -> 36 | D42: =C42*$B$22% -> 18 | E42: =C42*$B$23% -> 14.4 | F42: =C42*$B$26% -> 7.2 | G42: =if($A$39=$K$15,0,if($A$39=$K$16,0,if($A$39=$K$17,J16,if($A$39=$K$18,J17,if($A$39=$K$19,J18,if($A$39=$K$20,J19,J20)))))) -> 3 | H42: =if(G41-G42<0,0,G41-G42) -> 6 | I42: =H42*$B$24% -> -1.8 | J42: =H42*$B$25% -> -2.4
B43: =if($A$39=$K$15,J18,if($A$39=$K$16,J19,if($A$39=$K$17,J20,if($A$39=$K$18,J21,if($A$39=$K$19,J22,if($A$39=$K$20,0,if($A$39=$K$21,0,100))))))) -> 92 | C43: =if(B43-B42<0,0,B43-B42) -> 11 | D43: =C43*$B$22% -> 5.5 | E43: =C43*$B$23% -> 4.4 | F43: =C43*$B$26% -> 2.2 | G43: =if($A$39=$K$15,0,if($A$39=$K$16,0,if($A$39=$K$17,0,if($A$39=$K$18,J16,if($A$39=$K$19,J17,if($A$39=$K$20,J18,J19)))))) -> 0 | H43: =if(G42-G43<0,0,G42-G43) -> 3 | I43: =H43*$B$24% -> -0.9 | J43: =H43*$B$25% -> -1.2
D44: =sum(D41:D43) -> 35.5 | E44: =sum(E41:E43) -> 28.4 | F44: =sum(F41:F43) -> 14.2 | I44: =sum(I41:I43) -> -6.3 | J44: =sum(J41:J43) -> -8.4
C45: New score | D45: =D44+$A$41 -> 56.5 | E45: =E44+$A$41 -> 49.4 | F45: =F44+$A$41 -> 35.2 | I45: =I44+$A$41 -> 14.7 | J45: =J44+$A$41 -> 12.6
C46: New rating | D46: =VLOOKUP(D45,$J$15:$K$22,2,true) -> BBB | E46: =VLOOKUP(E45,$J$15:$K$22,2,true) -> BBB | F46: =VLOOKUP(F45,$J$15:$K$22,2,true) -> BB | I46: =VLOOKUP(I45,$J$15:$K$22,2,true) -> BB | J46: =VLOOKUP(J45,$J$15:$K$22,2,true) -> BB
C47: Diff score | D47: =D45-$A$41 -> 35.5 | E47: =E45-$A$41 -> 28.4 | F47: =F45-$A$41 -> 14.2 | I47: =I45-$A$41 -> -6.3 | J47: =J45-$A$41 -> -8.4
C48: Diff % | D48: =D47/$A$41 -> 1.6904762 | E48: =E47/$A$41 -> 1.352381 | F48: =F47/$A$41 -> 0.67619048 | I48: =I47/$A$41 -> -0.3 | J48: =J47/$A$41 -> -0.4

Sheet Scoring - fin experiment Spectr
C1: 0.9 | J1: 0.1
C2: fin score | O2: Score range | P2: Range
A3: Features_core | B3: max score cap | C3: core(70%) | D3: re arranged weights | E3: feature values-core | G3: Features_non core | H3: max score cap | I3: Non core(30%) | J3: re arranged weights | K3: feature values - non core | O3: -30 | P3: Very bad
A4: wc_utilisation_ltm_BSA_Tally | B4: 0 | C4: 0 | D4: =C4/SUM(C4,C5,C6,C7,C8,C9,C10) -> 0 | G4: net_cashflow_movement _tally_BSA | H4: 0 | J4: =I4/SUM($I$4:$I$10) -> #DIV/0! | K4: 0 | O4: -15 | P4: bad
A5: wc_utilisation_l6m_BSA_Tally | C5: 10 | D5: =C5/SUM(C4,C5,C6,C7,C8,C9,C10) -> 0.125 | E5: 0 | G5: customer_ageing_tally | J5: =I5/SUM($I$4:$I$10) -> #DIV/0! | K5: 0 | O5: 0 | P5: good
A6: effective_interest_rate_BSA_Tally | C6: 20 | D6: =C6/SUM(C4,C5,C6,C7,C8,C9,C10) -> 0.25 | E6: 15 | G6: supplier_ageing_tally | J6: =I6/SUM($I$4:$I$10) -> #DIV/0! | K6: 0 | O6: 15 | P6: v good
A7: churn_rate_BSA_tally | B7: 0 | C7: 20 | D7: =C7/SUM(C4,C5,C6,C7,C8,C9,C10) -> 0.25 | E7: 0 | G7: inventory_ageing_tally | J7: =I7/SUM($I$4:$I$10) -> #DIV/0! | K7: 0 | O7: 30
A8: Inward cheque returns_BSA_tally | C8: 10 | D8: =C8/SUM(C4,C5,C6,C7,C8,C9,C10) -> 0.125 | E8: 15 | G8: gross_profit_on_sales_GST_Tally | J8: =I8/SUM($I$4:$I$10) -> #DIV/0! | K8: 0 | O8: 30
A9: overutilisation_frequency_BSA_Tally | C9: 10 | D9: =C9/SUM(C4,C5,C6,C7,C8,C9,C10) -> 0.125 | E9: 0 | G9: avg_cash_balance_change_tally | J9: =I9/SUM($I$4:$I$10) -> #DIV/0! | K9: 0
A10: total_credit_to_loans_repaid_BSA_tally | C10: 10 | D10: =C10/SUM(C4,C5,C6,C7,C8,C9,C10) -> 0.125 | E10: 0 | G10: gross_sales_trend_gst_tally | J10: =I10/SUM($I$4:$I$10) -> #DIV/0! | K10: 0
C11: =sum(C4:C10) -> 80 | D11: =sum(D4:D10) -> 1 | I11: =sum(I4:I10) -> 0 | J11: =sum(J4:J10) -> #DIV/0! | R11: 1 | S11: 2 | T11: 3 | U11: 4
D12: Weighted score | E12: =SUMPRODUCT(D4:D10,E4:E10) -> 5.625 | K12: =SUMPRODUCT(J4:J10,K4:K10) -> #DIV/0! | L12: =E12*C1 -> 5.0625 | M12: =VLOOKUP(L12,$O$3:$P$8,2,true) -> good
J14: Overall rating 5t | L14: Range per rating
E15: 0-2 | F15: 10 | J15: 0 | K15: C | L15: =J16-J15 -> 3
E16: 44624 | F16: 20 | J16: 3 | K16: B | L16: =J17-J16 -> 7
E17: 44688 | F17: 30 | J17: 10 | K17: BB | L17: =J18-J17 -> 35
J18: 45 | K18: BBB | L18: =J19-J18 -> 35 | R18: 3
J19: 80 | K19: A | L19: =J20-J19 -> 12
J20: 92 | K20: AA | L20: =J21-J20 -> 4
A21: Data avail (flags) | B21: Actual value (test) Select one of data avail (flag) | C21: Fin, GST, EPF | D21: GST, EPF | E21: Fin and GST | F21: GST | G21: If period of data avail is less than 6 months (half of final) | J21: 96 | K21: AAA | L21: =J22-J21 -> 4
A22: Boost v good % | B22: =G22 -> 30 | C22: 50 | D22: =C22+5 -> 55 | E22: 60 | F22: =C22+20 -> 70 | G22: =E22/2 -> 30 | J22: 100
A23: Boost good % | B23: =G23 -> 25 | C23: 40 | D23: =C23+5 -> 45 | E23: 50 | F23: =C23+20 -> 60 | G23: =E23/2 -> 25
A24: Boost bad % | B24: =G24 -> -20 | C24: =-C23+10 -> -30 | D24: =C24+5 -> -25 | E24: =-E23+10 -> -40 | F24: =C24+20 -> -10 | G24: =E24/2 -> -20
A25: Boost v bad % | B25: =G25 -> -25 | C25: =-C22+10 -> -40 | D25: =C25+5 -> -35 | E25: =-E22+10 -> -50 | F25: =C25+20 -> -20 | G25: =E25/2 -> -25
A26: Boost avg | B26: =G26 -> 12.5 | C26: =C23/2 -> 20 | D26: =D23/2 -> 22.5 | E26: =E23/2 -> 25 | F26: =F23/2 -> 30 | G26: =E26/2 -> 12.5
A30: When only GST AV | H30: When FIN and GST AV | J30: When GST EPFO AV | N30: When FIN GST EPFO AV
A31: consent score | B31: Fin | C31: GST | D31: EPFO | E31: Original TSR | F31: TSR consent | H31: consent score | I31: Fin | J31: GST | K31: EPFO | M31: TSR | O31: consent score | P31: Fin | Q31: GST | R31: EPFO | T31: TSR
B32: 0.35 | C32: 2 | D32: 2 | F32: 0.46 | I32: 0.35 | J32: 2 | K32: 2 | M32: 0.46 | P32: 0.35 | Q32: 2 | R32: 2 | T32: 0.46
A33: vgood | B33: 0.749 | C33: 2 | D33: 2 | E33: 0.818 | F33: 0.946 | H33: vgood | I33: 0.692 | J33: 2 | K33: 2 | L33: 0.781 | M33: 0.888 | O33: vgood | P33: 0.635 | Q33: 2 | R33: 2 | S33: 0.737 | T33: 0.8485
A34: good | B34: 0.692 | C34: 2 | D34: 2 | E34: 0.781 | F34: 0.888 | H34: good | I34: 0.635 | J34: 2 | K34: 2 | L34: 0.737 | M34: 0.848 | O34: good | P34: 0.578 | Q34: 2 | R34: 2 | S34: 0.689 | T34: 0.797
A35: avg | B35: 0.521 | C35: 2 | D35: 2 | E35: 0.636 | H35: avg | I35: 0.4925 | J35: 2 | K35: 2 | L35: 0.608 | O35: avg | P35: 0.464 | Q35: 2 | R35: 2 | S35: 0.58
A36: bad | B36: 0.175 | C36: 2 | D36: 2 | E36: 0.294 | F36: 0.147 | H36: bad | I36: 0.21 | J36: 2 | K36: 2 | L36: 0.326 | M36: 0.195 | O36: bad | P36: 0.245 | Q36: 2 | R36: 2 | S36: 0.35 | T36: 0.245
A37: vbad | B37: 0.14 | C37: 2 | D37: 2 | E37: 0.265 | F37: 0.106 | H37: vbad | I37: 0.175 | J37: 2 | K37: 2 | L37: 0.294 | M37: 0.875 | O37: vbad | P37: 0.21 | Q37: 2 | R37: 2 | S37: 0.326 | T37: 0.195
A39: =VLOOKUP(A41,J15:K22,2,true) -> BB
A40: Fin Model score | B40: Upper limits per upper rating (assuming max boost of +2 notches) | C40: Points available for movement (upward) | D40: V good | E40: Good | F40: Avg | G40: Lower limits per lower rating (assuming max cut of -2 notches) | H40: Points available for movement (downward) | I40: Bad | J40: V Bad
A41: 37 | B41: =if($A$39=$K$15,J16,if($A$39=$K$16,J17,if($A$39=$K$17,J18,if($A$39=$K$18,J19,if($A$39=$K$19,J20,if($A$39=$K$20,J21,100)))))) -> 45 | C41: =B41-A41 -> 8 | D41: =C41*$B$22% -> 2.4 | E41: =C41*$B$23% -> 2 | F41: =C41*$B$26% -> 1 | G41: =if($A$39=$K$15,0,if($A$39=$K$16,J16,if($A$39=$K$17,J17,if($A$39=$K$18,J18,if($A$39=$K$19,J19,if($A$39=$K$20,J20,J21)))))) -> 10 | H41: =A41-G41 -> 27 | I41: =H41*$B$24% -> -5.4 | J41: =H41*$B$25% -> -6.75
B42: 81 | C42: =if(B42-B41<0,0,B42-B41) -> 36 | D42: =C42*$B$22% -> 10.8 | E42: =C42*$B$23% -> 9 | F42: =C42*$B$26% -> 4.5 | G42: =if($A$39=$K$15,0,if($A$39=$K$16,0,if($A$39=$K$17,J16,if($A$39=$K$18,J17,if($A$39=$K$19,J18,if($A$39=$K$20,J19,J20)))))) -> 3 | H42: =if(G41-G42<0,0,G41-G42) -> 7 | I42: =H42*$B$24% -> -1.4 | J42: =H42*$B$25% -> -1.75
B43: =if($A$39=$K$15,J18,if($A$39=$K$16,J19,if($A$39=$K$17,J20,if($A$39=$K$18,J21,if($A$39=$K$19,J22,if($A$39=$K$20,0,if($A$39=$K$21,0,100))))))) -> 92 | C43: =if(B43-B42<0,0,B43-B42) -> 11 | D43: =C43*$B$22% -> 3.3 | E43: =C43*$B$23% -> 2.75 | F43: =C43*$B$26% -> 1.375 | G43: =if($A$39=$K$15,0,if($A$39=$K$16,0,if($A$39=$K$17,0,if($A$39=$K$18,J16,if($A$39=$K$19,J17,if($A$39=$K$20,J18,J19)))))) -> 0 | H43: =if(G42-G43<0,0,G42-G43) -> 3 | I43: =H43*$B$24% -> -0.6 | J43: =H43*$B$25% -> -0.75
D44: =sum(D41:D43) -> 16.5 | E44: =sum(E41:E43) -> 13.75 | F44: =sum(F41:F43) -> 6.875 | I44: =sum(I41:I43) -> -7.4 | J44: =sum(J41:J43) -> -9.25
C45: New score | D45: =D44+$A$41 -> 53.5 | E45: =E44+$A$41 -> 50.75 | F45: =F44+$A$41 -> 43.875 | I45: =I44+$A$41 -> 29.6 | J45: =J44+$A$41 -> 27.75
C46: New rating | D46: =VLOOKUP(D45,$J$15:$K$22,2,true) -> BBB | E46: =VLOOKUP(E45,$J$15:$K$22,2,true) -> BBB | F46: =VLOOKUP(F45,$J$15:$K$22,2,true) -> BB | I46: =VLOOKUP(I45,$J$15:$K$22,2,true) -> BB | J46: =VLOOKUP(J45,$J$15:$K$22,2,true) -> BB
C47: Diff score | D47: =D45-$A$41 -> 16.5 | E47: =E45-$A$41 -> 13.75 | F47: =F45-$A$41 -> 6.875 | I47: =I45-$A$41 -> -7.4 | J47: =J45-$A$41 -> -9.25
C48: Diff % | D48: =D47/$A$41 -> 0.44594595 | E48: =E47/$A$41 -> 0.37162162 | F48: =F47/$A$41 -> 0.18581081 | I48: =I47/$A$41 -> -0.2 | J48: =J47/$A$41 -> -0.25

Sheet FLow
A2: Testing suggestions
C5: TAT (hours)
A6: Business shares PDF | E6: EPDF
A7: Conversion to excel | C7: 1
A8: Computation of fin features | C8: 6 | E8: NA
A9: Computation of consent fin score | C9: NA
A10: Computation of variable score (function of data cateogories avail and period avail) | C10: NA
A11: Updation of model fin score = fin score with consent | C11: NA
A12: Computation of final TSR score basis fin score basis consent | C12: NA
A13: Computation of non fin consent features | C13: 4
A14: Computation of consent non fin score | C14: NA
A15: Computation of variable score (function of data cateogories avail and period avail) | C15: NA
A16: Updation of modelTSR score = TSR score with consent | C16: NA
A17: Updation of non fin score in report (model driven non fin score +/- % change in TSR with consent | C17: NA
A19: Kalyan to define flow
A20: Ordering of report
A21: Consent feature value csv

Sheet SCPL Spectrum non finscore
A1: 5562991a6d6f6f3762099910
A3: SCPL
A4: When FIN GST EPFO AV
B5: consent score | C5: Fin | D5: GST | E5: EPFO | F5: original tsr | G5: TSR with consent | H5: TSR Rating | I5: change in fin | J5: change in tsr pd
B6: Model output | C6: 0.21 | D6: 4 | E6: 2 | F6: 0.15 | H6: BB | I6: =(C7/C6)-1 -> -0.3 | J6: =G7/F6-1 -> -0.4
B7: Model output+consent | C7: 0.147 | D7: 4 | E7: 2 | F7: 0.13 | G7: 0.09 | H7: BB
C8: =C7/C6-1 -> -0.3 | G8: =G7/F7-1 -> -0.30769231
E10: Non fin | F10: =0.38*(1+G8) -> 0.26307692
A12: Spectrum
A13: When FIN GST EPFO AV
B14: consent score | C14: Fin | D14: GST | E14: EPFO | F14: original tsr | G14: TSR with consent | H14: TSR Rating | I14: change in fin | J14: change in tsr pd
B15: Model output | C15: 0.37 | D15: 3 | E15: 2 | F15: 0.369 | H15: BB | I15: =(C16/C15)-1 -> 0.37162162 | J15: =G16/F15-1 -> 0.12195122
B16: Model output+consent | C16: 0.5075 | D16: 3 | E16: 2 | F16: 0.505 | G16: 0.414 | H16: BB
G17: =G16/F16-1 -> -0.18019802
E19: Non fin | F19: =0.66*(1+G17) -> 0.54106931

Sheet Scoring - fin 
C1: 0.7 | J1: =100%-C1 -> 0.3
C2: fin score | O2: Score range | P2: Range
A3: Features_core | B3: max score cap | C3: core(70%) | D3: re arranged weights | E3: feature values-core | G3: Features_non core | H3: max score cap | I3: Non core(30%) | J3: re arranged weights | K3: feature values - non core | O3: -30 | P3: Very bad
A4: WC utilisation_bank statement _BSA | B4: 0 | C4: 0.35 | D4: =C4/SUM(C4,C5,C6,C7,C8) -> 0.36842105 | E4: -15 | F4: =D4*E4 -> -5.5263158 | G4: Increase in customer ageing | H4: 0 | I4: 0 | J4: =I4/SUM($I$4:$I$8) -> 0 | K4: 0 | O4: -15 | P4: bad
A5: effecttive interest rate_BSA | C5: 0.35 | D5: =C5/SUM(C4,C5,C6,C7,C8) -> 0.36842105 | E5: -15 | F5: =D5*E5 -> -5.5263158 | G5: Gross profit on GST sales (GST) | I5: 0 | J5: =I5/SUM($I$4:$I$8) -> 0 | K5: 0 | O5: 0 | P5: good
A6: Churn rate_BSA | C6: 0.2 | D6: =C6/SUM(C4,C5,C6,C7,C8) -> 0.21052632 | E6: 0 | F6: =D6*E6 -> 0 | G6: Avg cash balance change | I6: 0 | J6: =I6/SUM($I$4:$I$8) -> 0 | K6: 0 | O6: 15 | P6: v good
A7: funds_insufficient_cheque returns_BSA | B7: 0 | C7: 0.05 | D7: =C7/SUM(C4,C5,C6,C7,C8) -> 0.052631579 | E7: 15 | F7: =D7*E7 -> 0.78947368 | G7: gross sales trend_gst | I7: 0 | J7: =I7/SUM($I$4:$I$8) -> 0 | K7: 0 | O7: 30
A8: Net cashflow movement _Tally | C8: 0 | D8: =C8/SUM(C4,C5,C6,C7,C8) -> 0 | E8: -30 | F8: =D8*E8 -> 0 | G8: WC utilisation_bank statement _BSA l6m | I8: 0.05 | J8: =I8/SUM($I$4:$I$8) -> 1 | K8: -15
I9: =sum(I3:I8) -> 0.05 | J9: =sum(J3:J7) -> 0
C10: =sum(C4:C8) -> 0.95 | D10: =sum(D4:D8) -> 1 | R10: 1 | S10: 2 | T10: 3 | U10: 4
D11: Weighted score | E11: =SUMPRODUCT(D4:D8,E4:E8) -> -10.263158 | K11: =SUMPRODUCT(J4:J8,K4:K8) -> -15 | L11: =if(K11=0,E11*1,E11*C1+K11*J1) -> -11.684211 | M11: =VLOOKUP(L11,$O$3:$P$7,2,true) -> bad
J13: Overall rating 5t | L13: Range per rating
J14: 0 | K14: C | L14: =J15-J14 -> 3
J15: 3 | K15: B | L15: =J16-J15 -> 7
J16: 10 | K16: BB | L16: =J17-J16 -> 35
J17: 45 | K17: BBB | L17: =J18-J17 -> 35 | R17: 3
J18: 80 | K18: A | L18: =J19-J18 -> 12
J19: 92 | K19: AA | L19: =J20-J19 -> 4
A20: Data avail (flags) | B20: Actual value (test) Select one of data avail (flag) | C20: Fin, GST, EPF | D20: GST, EPF | E20: Fin and GST | F20: GST | G20: If period of data avail is less than 6 months (half of final) | J20: 96 | K20: AAA | L20: =J21-J20 -> 4
A21: Boost v good % | B21: =E21 -> 60 | C21: 50 | D21: =C21+10 -> 60 | E21: 60 | F21: =E21+10 -> 70 | G21: =B21/2 -> 30 | J21: 100
A22: Boost good % | B22: =E22 -> 50 | C22: 40 | D22: =C22+10 -> 50 | E22: 50 | F22: =E22+10 -> 60 | G22: =B22/2 -> 25
A23: Boost bad % | B23: -20 | C23: =-C22+10 -> -30 | D23: =-D22+10 -> -40 | E23: =-E22+10 -> -40 | F23: =-F22+10 -> -50 | G23: =B23/2 -> -10
A24: Boost v bad % | B24: =E24 -> -50 | C24: =-C21+10 -> -40 | D24: =-D21+10 -> -50 | E24: =-E21+10 -> -50 | F24: =-F21+10 -> -60 | G24: =B24/2 -> -25
A28: =VLOOKUP(A30,J14:K21,2,true) -> B
A29: Fin Model score | B29: Upper limits per upper rating (assuming max boost of +2 notches) | C29: Points available for movement (upward) | D29: V good | E29: Good | F29: Lower limits per lower rating (assuming max cut of -2 notches) | G29: Points available for movement (downward) | H29: Bad | I29: V Bad
A30: 6 | B30: =if($A$28=$K$14,J15,if($A$28=$K$15,J16,if($A$28=$K$16,J17,if($A$28=$K$17,J18,if($A$28=$K$18,J19,if($A$28=$K$19,J20,100)))))) -> 10 | C30: =B30-A30 -> 4 | D30: =C30*$B$21% -> 2.4 | E30: =C30*$B$22% -> 2 | F30: =if($A$28=$K$14,0,if($A$28=$K$15,J15,if($A$28=$K$16,J16,if($A$28=$K$17,J17,if($A$28=$K$18,J18,if($A$28=$K$19,J19,J20)))))) -> 3 | G30: =A30-F30 -> 3 | H30: =G30*$B$23% -> -0.6 | I30: =G30*$B$24% -> -1.5
B31: =if($A$28=$K$14,J16,if($A$28=$K$15,J17,if($A$28=$K$16,J18,if($A$28=$K$17,J19,if($A$28=$K$18,J20,if($A$28=$K$19,J21,if($A$28=$K$20,0,100))))))) -> 45 | C31: =if(B31-B30<0,0,B31-B30) -> 35 | D31: =C31*$B$21% -> 21 | E31: =C31*$B$22% -> 17.5 | F31: =if($A$28=$K$14,0,if($A$28=$K$15,0,if($A$28=$K$16,J15,if($A$28=$K$17,J16,if($A$28=$K$18,J17,if($A$28=$K$19,J18,J19)))))) -> 0 | G31: =if(F30-F31<0,0,F30-F31) -> 3 | H31: =G31*$B$23% -> -0.6 | I31: =G31*$B$24% -> -1.5
B32: =if($A$28=$K$14,J17,if($A$28=$K$15,J18,if($A$28=$K$16,J19,if($A$28=$K$17,J20,if($A$28=$K$18,J21,if($A$28=$K$19,0,if($A$28=$K$20,0,100))))))) -> 80 | C32: =if(B32-B31<0,0,B32-B31) -> 35 | D32: =C32*$B$21% -> 21 | E32: =C32*$B$22% -> 17.5 | F32: =if($A$28=$K$14,0,if($A$28=$K$15,0,if($A$28=$K$16,0,if($A$28=$K$17,J15,if($A$28=$K$18,J16,if($A$28=$K$19,J17,J18)))))) -> 0 | G32: =if(F31-F32<0,0,F31-F32) -> 0 | H32: =G32*$B$23% -> 0 | I32: =G32*$B$24% -> 0
D33: =sum(D30:D32) -> 44.4 | E33: =sum(E30:E32) -> 37 | H33: =sum(H30:H32) -> -1.2 | I33: =sum(I30:I32) -> -3
C34: New score | D34: =D33+$A$30 -> 50.4 | E34: =E33+$A$30 -> 43 | H34: =H33+$A$30 -> 4.8 | I34: =I33+$A$30 -> 3
C35: New rating | D35: =VLOOKUP(D34,$J$14:$K$21,2,true) -> BBB | E35: =VLOOKUP(E34,$J$14:$K$21,2,true) -> BB | H35: =VLOOKUP(H34,$J$14:$K$21,2,true) -> B | I35: =VLOOKUP(I34,$J$14:$K$21,2,true) -> B
C36: Diff score | D36: =D34-$A$30 -> 44.4 | E36: =E34-$A$30 -> 37 | H36: =H34-$A$30 -> -1.2 | I36: =I34-$A$30 -> -3
C37: Diff % | D37: =D36/$A$30 -> 7.4 | E37: =E36/$A$30 -> 6.1666667 | H37: =H36/$A$30 -> -0.2 | I37: =I36/$A$30 -> -0.5
A39: Risk tree map area
A40: 0.32857143 | D40: =$A40*(1+$B$21%) -> 0.52571429 | E40: =$A40*(1+$B$22%) -> 0.49285714 | H40: =$A40*(1+abs($B$23%)) -> 0.39428571 | I40: =$A40*(1+abs($B$24%)) -> 0.49285714
A41: 0.32857143 | D41: =A41*(1+$B$21%) -> 0.52571429 | E41: =$A41*(1+$B$22%) -> 0.49285714 | H41: =$A41*(1+abs($B$23%)) -> 0.39428571 | I41: =$A41*(1+abs($B$24%)) -> 0.49285714
A42: 0.18571429 | D42: =A42*(1+$B$21%) -> 0.29714286 | E42: =$A42*(1+$B$22%) -> 0.27857143 | H42: =$A42*(1+abs($B$23%)) -> 0.22285714 | I42: =$A42*(1+abs($B$24%)) -> 0.27857143
A43: 0.15714286 | D43: =A43*(1+$B$21%) -> 0.25142857 | E43: =$A43*(1+$B$22%) -> 0.23571429 | H43: =$A43*(1+abs($B$23%)) -> 0.18857143 | I43: =$A43*(1+abs($B$24%)) -> 0.23571429

Sheet WIP
G1: Account for CC OD will always be in debit. Can you prepare a cash flow
A4: Feature names | B4: Score (input) range = -30 to 70 | C4: Weight | D4: Model | E4: Consent data source | F4: =70%/2 -> 0.35 | K4: Model output | L4: Consent score | M4: Change in model score | N4: Final score
A5: Feature consent fin soa_1 | B5: -15 | C5: 0.35 | D5: Fin | E5: Bank statements | F5: Core | G5: net total inflow/total inflow | H5: Churning | J5: Fin | K5: 0.5 | L5: =C9 -> 23.25 | M5: =(K5*L5*0.4)/100 -> 0.0465 | N5: =K5+M5 -> 0.5465
A6: Feature consent fin soa_2 | B6: 30 | C6: 0.35 | D6: Fin | E6: Bank statements | F6: Core | G6: Net inlow/total inflow | J6: GST | K6: 0.8 | L6: =C14 -> 60 | M6: =(K6*L6*0.4)/100 -> 0.192 | N6: =K6+M6 -> 0.992
A7: Feature consent fin soa_3 | B7: 50 | C7: 0.15 | D7: Fin | E7: Bank statements | F7: Non core | G7: Avg cc od utilisation | H7: Cheque returns | J7: TSR PD | K7: 0.5 (input fin score is final fin model score = 0.54775 (input gst score is final gst model score = 0.992) | L7: =C20 -> 52.5 | M7: =(0.5*L7*0.4)/100 -> 0.105 | N7: =0.5+M7 -> 0.605
A8: Feature consent fin gst_1 | B8: 70 | C8: 0.15 | D8: Fin | E8: GST | F8: Non core | G8: Change in avg eod balance. year t-1 to year t
A9: Feature consent fin all_weighted score | C9: =SUMPRODUCT(B5:B8,C5:C8) -> 23.25 | G9: Value of cash dr./total or avg debits Value of cash cr./total or avg credits | M9: Change in model score
G10: Salary payments | K10: - Max positive impact for few features to only be "no impact" - | M10: - as a % - as points - a % or points which ever is lower - capping more than two rating shifts
G11: Significant cash transactions | M11: If fin score is between X to X+20 (i.e. bucket)..range
A12: Feature consent gst gst_2 | B12: 50 | C12: 0.5 | D12: GST | E12: GST | G12: Total debit count in cash / total debit count | L12: 0.2
A13: Feature consent gst gst_3 | B13: 70 | C13: 0.5 | D13: GST | E13: GST | G13: Total credit count in cash / total debit count | K13: 0.2 | L13: =K13*(1-$L$12) -> 0.16 | M13: =K13-L13 -> 0.04 | N13: =K13*(1+$L$12) -> 0.24
A14: Feature consent gst all_weighted score | C14: =SUMPRODUCT(B12:B13,C12:C13) -> 60 | K14: 0.4 | L14: =K14*(1-$L$12) -> 0.32 | M14: =K14-L14 -> 0.08 | N14: =K14*(1+$L$12) -> 0.48
K15: 0.6 | L15: =K15*(1-$L$12) -> 0.48 | M15: =K15-L15 -> 0.12 | N15: =K15*(1+$L$12) -> 0.72
A16: Feature consent soa other_1 | B16: 70 | C16: 0.25 | D16: Meta model TSR PD | E16: Bank statements | G16: 1 | H16: 0.25 | K16: 0.8 | L16: =K16*(1-$L$12) -> 0.64 | M16: =K16-L16 -> 0.16 | N16: =K16*(1+$L$12) -> 0.96
A17: Feature consent gst other_2 | B17: 50 | C17: 0.25 | D17: Meta model TSR PD | E17: GST | G17: 2 | H17: 0.25 | K17: 0.95 | L17: =K17*(1-$L$12) -> 0.76 | M17: =K17-L17 -> 0.19 | N17: =K17*(1+$L$12) -> 1.14
A18: Feature consent soa other_3 | B18: 30 | C18: 0.25 | D18: Meta model TSR PD | E18: Bank statements | G18: 3
A19: Feature consent gst other_4 | B19: 60 | C19: 0.25 | D19: Meta model TSR PD | E19: GST | G19: 4 | K19: next bucket 75th point
A20: Feature consent other all_weighted score | C20: =SUMPRODUCT(B16:B19,C16:C19) -> 52.5 | G20: 5
H21: 0.7

Sheet Sheet1
A1: What you need? | F1: Discuss
A2: Bank statements for all current accounts and working capital loan accounts. | F2: Feasibliity?
A3: Period - For three financial years Should include latest financial year which was concluded | F3: Rule based approach with top 5 params as starter
A4: Perfious to provide an excel output | B4: ok | F4: Clarity on docs required to BD team
A6: Feature | B6: Extent of data availbality driven clarity | C6: Comment on challenges | D6: Rationale for the feature | F6: Schedule interview | G6: 5 to 5:30
A7: IN last XX months, monthly utilisation over 90% | B7: High | F7: Focus areas assignment
A8: Increasing sanctioned limits | B8: High | F8: Subir ML team limitation
A9: Inward cheque bounce count for those issued above a threshold. Threshold can be avg of cheques issued in last XX years | B9: Medium
A10: Round tripping instances | B10: Low
A11: No of days account remained over 100% utilisation | B11: High
A12: Count of cheque outward (higher count suggest poor customer profile) AS % of cheque received or period over period trend | B12: Medium
A13: No of debits Change period to period | B13: High
A14: No of credits Change period to period | B14: High
A15: Avg dr. balance in a month | B15: High
A16: Avg cr. balance in a month | B16: High
A17: Total debit value / dr. transactions | B17: High
A18: Total credit value / cr. transactions | B18: High
A19: Total cr. transaction value / total sales | B19: Medium
A20: Total interest paid Ratios regarding this. Eg. intrest paid / cr. transactions (roxy for sales) Trend approach to conclude increasing or decreasing int. | B20: Medium | F20: How to identify bank holiday trasnaction
A21: No of debit transactions with related parties | B21: Medium
A22: No of credit transactions related parties | B22: Medium
A23: Heavy cash withdrawal in loan accounts. | B23: High
A26: CHeque outward to parties which contributed to highest funds received (% of duration period)
A27: Interest paid to total of credit in a month (use trend here rather than value)
A28: No of transactions where Dr and Cr is to same party or presence of parties in both Dr Cr
A31: Average utilisation

Sheet BS feat_draft
A1: Avg. utilisation in last 6 months | B1: Weight=35% | D1: Ratio of Avg. Debit to Avg. Credit in Last 12 Months (Churning) | E1: Wegiht=20% | G1: Concentration risk - funds received from single source | H1: Weight = 5% | L1: Fin score model driven | M1: 55 | N1: Input to meta model
A2: More than 100% | B2: -30 | D2: X <100% | E2: 70 | G2: > 50% | H2: -30 | I2: top 5 (funds received) | L2: Decline basis consent fin | M2: 0.2
A3: 90-100% | B3: -15 | D3: 100 to 110 % | E3: 50 | G3: 40 to 50% | H3: -15 | I3: <10 | J3: 0 | L3: New fin score | M3: =M1*0.8 -> 44 | N3: New Input to meta model
A4: 70 to 90% | B4: 10 | D4: 110 to 125% | E4: 10 | G4: 30 to 40% | H4: 10 | I4: 10 to 20 | J4: -5
A5: 50 to 70% | B5: 30 | D5: 125-150 % | E5: -15 | G5: 20 to 30% | H5: 20 | I5: 20-50 | J5: -15
A6: 30 to 50% | B6: 50 | D6: Greater than 150% | E6: -30 | G6: 10 to 20% | H6: 50 | I6: >50 | J6: -30
A7: Less than 30% | B7: 70 | G7: 0 to 10% | H7: 70
A9: Inward cheque returns (negative factor only) | D9: Related party transactions | E9: Weight = 25% | G9: Concentration risk - funds remitted to single source | H9: Weight = 5% | O9: 50 | P9: 0.35
A10: No inward return | B10: 0 | C10: 0 | D10: > 20% | E10: -30 | G10: > 50% | H10: -30 | I10: top 5 (funds paid) | L10: Consent fin 1 | O10: 50 | P10: 0.2
A11: 1 to 5 (if CC account then cheque shouldnt bounce due to insufficient funds given it is within drawing power) | B11: -5 | C11: -15 | D11: 20-10% | E11: -15 | G11: 40 to 50% | H11: -15 | I11: <10 | J11: 0 | L11: Consent fin 2 | O11: -15 | P11: 0.25
A12: more than 5 | B12: -10 | C12: -30 | D12: 5-10% | E12: 10 | G12: 30 to 40% | H12: 10 | I12: 10 to 20 | J12: -10 | L12: Weighted consent fin score | M12: 50 | N12: 0.2 | O12: % change in fin score | P12: 0.1
D13: 2-5% | E13: 30 | G13: 20 to 30% | H13: 20 | I13: 20-50 | J13: -15 | O13: 20 | P13: 0.05
C14: 30 | D14: 0 to 2% | E14: 70 | G14: 10 to 20% | H14: 50 | I14: >50 | J14: -30 | O14: 70 | P14: 0.05
G15: 0 to 10% | H15: 70 | L15: Consent non fin 1
A16: No of times account remained over utilised(negative factor only) | D16: % interest payout on average utilisation | E16: Weight = 10% | L16: Consent non fin 2
A17: Never overutilised | B17: 0 | D17: 0-5% | E17: 70 | G17: Avg cash balance | L17: Weighted non fin consent | N17: % change in non fin score
D18: 5-10% | E18: 50
D19: 10-12% | E19: 10 | L19: Third level is overall PD
D20: 12-18% | E20: -15
D21: >18% | E21: -30 | F21: Check if indeed will get such values
A23: Final score on 6 core features for party | B23: =sumproduct(O9:O14,P9:P14) -> 28.25
A24: Scaled score on 6 score features | B24: =B23+30 -> 58.25
A25: Adjusted scaled score basis 6 features | B25: =B24+0 -> 58.25
F30: 100
A31: Routing of funds | D31: TL | E31: WC L
A32: Common parties | D32: 100 | E32: 100 | F32: Day 1 | H32: 20
A33: 1 to 5 | C33: -10 | D33: -20 | E33: -20
A34: 5 to 10 | C34: -30 | D34: -20 | E34: =E32+E33 -> 80 | F34: Day 2
E35: -20
E36: 60 | F36: Day 3
E37: 10
E38: 70 | F38: Day 4
E39: 70 | F39: Day 5
E40: 70 | F40: Day 6
E41: 70 | F41: Day 7
D44: 8 | E44: bank | G44: 0.3
F45: tsr
D46: 8 | E46: gstn c | G46: 0.5
G48: 0.4
B50: epfo | C50: gstn | D50: fin | E50: bank | F50: gstn c | G50: output
B51: best | C51: best | D51: best | E51: worst | G51: medium
B53: worst | C53: worst | D53: worst
D65: (10-15+20+50)/(70+70+70+70) | E65: 0.43 | F65: 0.43
B68: 2018-19 | C68: 44317
B69: 2018-19 | C69: Older date
